<?xml version="1.0" encoding="UTF-8"?>
<root>
	<row>
		<name>brandy_book_v1_post_1</name>
		<title><![CDATA[The Hidden Gems of Independent Bookstores]]></title>
		<content>Looking for a unique reading experience? Independent bookstores are treasure troves
			of hidden gems. From rare editions to self-published works, these stores often have
			books that you won’t find in chain stores. Plus, the personal touch from store owners
			and staff can lead to fantastic recommendations that align perfectly with your tastes.
			Explore your local indie bookstore and discover something truly special. </content>
		<featured_image>http://img.wpbrandy.com/uploads/book-post-1.png</featured_image>
		<category domain="category" nicename="Bookstore Insights"><![CDATA[Bookstore Insights]]></category>
		<category domain="post_tag" nicename="Independent Bookstores"><![CDATA[Independent Bookstores]]></category>
		<category domain="post_tag" nicename="Hidden Gems"><![CDATA[Hidden Gems]]></category>
		<category domain="post_tag" nicename="Rare Editions"><![CDATA[Rare Editions]]></category>
		<category domain="post_tag" nicename="Local Bookstores"><![CDATA[Local Bookstores]]></category>
		<comment>I absolutely agree! I found a first edition of my favorite novel in a small indie
			bookstore downtown. It’s such a joy to support local businesses and find unique reads!</comment>
		<comment>Definitely! I love how indie bookstores often have that special vibe that chain
			stores lack.</comment>
	</row>
	<row>
		<name>brandy_book_v1_post_2</name>
		<title>The Joy of Bookstore Cafés</title>
		<content>There’s nothing quite like the experience of browsing through books while sipping a
			freshly brewed coffee. Bookstore cafés offer a cozy haven where you can lose yourself in
			a book or chat about literature with fellow readers. Many stores now have a café or tea
			bar, making it a perfect spot for book lovers to unwind and indulge their literary
			passions.</content>
		<featured_image>http://img.wpbrandy.com/uploads/book-post-2.png</featured_image>
		<category domain="category" nicename="Bookstore Experiences"><![CDATA[Bookstore Experiences]]></category>
		<category domain="category" nicename="Bookstore Cafés"><![CDATA[Bookstore Cafés]]></category>
		<category domain="post_tag" nicename="Coffee and Books"><![CDATA[Coffee and Books]]></category>
		<category domain="post_tag" nicename="Cozy Reading Spots"><![CDATA[Cozy Reading Spots]]></category>
		<category domain="post_tag" nicename="Bookstore Culture"><![CDATA[Bookstore Culture]]></category>
		<comment>I love spending my Saturday afternoons in bookstore cafés! The atmosphere is so
			relaxing, and I always leave with a new book or two. Plus, the coffee is usually
			fantastic!</comment>
		<comment>Yes! I think the combination of books and coffee is just magical. It's like the
			perfect recipe for a great day.</comment>
	</row>
	<row>
		<name>brandy_book_v1_post_3</name>
		<title>How Bookstores Curate Their Collections</title>
		<content>Ever wondered how bookstores choose which books to stock? Many bookstores curate
			their collections based on reader interests, current trends, and staff recommendations.
			This careful selection process ensures that you’ll find a thoughtfully chosen variety of
			books, from bestsellers to niche topics. Next time you’re in a bookstore, take a moment
			to appreciate the effort that goes into creating such a unique collection.</content>
		<featured_image>http://img.wpbrandy.com/uploads/book-post-3.png</featured_image>
		<category domain="category" nicename="Bookstore Operations"><![CDATA[Bookstore Operations]]></category>
		<category domain="post_tag" nicename="Book Curation"><![CDATA[Book Curation]]></category>
		<category domain="post_tag" nicename="Book Selection"><![CDATA[Book Selection]]></category>
		<category domain="post_tag" nicename="Staff Picks"><![CDATA[Staff Picks]]></category>
		<comment>I’ve always been curious about this! It’s amazing how much thought and effort goes
			into curating the shelves. It definitely makes the browsing experience more enjoyable!</comment>
		<comment>True! I often find books I wouldn’t have picked up elsewhere just because the staff
			recommendations are spot on.</comment>
	</row>
	<row>
		<name>brandy_book_v1_post_4</name>
		<title>The Rise of Bookstore Events</title>
		<content>Bookstores are becoming hubs of community engagement, thanks to a wide array of
			events. From author signings and book launches to poetry readings and book clubs, these
			events create vibrant spaces for readers to connect. Check out your local bookstore’s
			event calendar—there might be a literary event that piques your interest!</content>
		<featured_image>http://img.wpbrandy.com/uploads/book-post-4.png</featured_image>
		<category domain="category" nicename="Bookstore Events"><![CDATA[Bookstore Events]]></category>
		<category domain="post_tag" nicename="Author Signings"><![CDATA[Author Signings]]></category>
		<category domain="post_tag" nicename="Book Launches"><![CDATA[Book Launches]]></category>
		<comment>I recently attended a book signing at my local bookstore, and it was such a fun
			experience! It’s great to see stores fostering a sense of community through these
			events.</comment>
		<comment>Agreed! The events make bookstores so much more than just places to buy books. It’s
			like being part of a literary community.
		</comment>
	</row>
	<row>
		<name>brandy_plants_the_ultimate_guide_to_indoor_herb_gardens</name>
		<title>The Ultimate Guide to Indoor Herb Gardens</title>
		<content>Indoor herb gardens are perfect for those who love to cook with fresh
			ingredients...</content>
		<featured_image>http://img.wpbrandy.com/uploads/book-post-5.png</featured_image>
		<category domain="category" nicename="indoor_gardening"><![CDATA[Indoor Gardening]]></category>
		<category domain="category" nicename="herbs"><![CDATA[Herbs]]></category>
		<comment>This is the kind of content that makes me grateful to be alive. Thank you!</comment>
		<comment>You've got a way of making the world a more beautiful place. Thank you!</comment>
	</row>
	<row>
		<name>brandy_book_v1_post_5</name>
		<title>The Evolution of Bookstore Design</title>
		<content>Bookstores are not just places to buy books; they are becoming immersive
			experiences. Modern bookstore design often incorporates elements like comfortable
			seating, interactive displays, and thematic decor. These design choices make browsing
			more enjoyable and encourage readers to spend more time exploring the shelves. What’s
			your favorite bookstore design trend?</content>
		<featured_image>http://img.wpbrandy.com/uploads/book-post-6.png</featured_image>
		<category domain="category" nicename="Store Design"><![CDATA[Store Design]]></category>
		<category domain="post_tag" nicename="Bookstore Design"><![CDATA[Bookstore Design]]></category>
		<category domain="post_tag" nicename="Store Layout"><![CDATA[Store Layout]]></category>
		<category domain="post_tag" nicename="Reading Nooks"><![CDATA[Reading Nooks]]></category>
		<comment>I love bookstores that have cozy reading nooks and eclectic decor. It makes the
			whole experience feel so much more inviting and enjoyable!</comment>
		<comment>The interactive displays are great! They really make it fun to explore new genres
			and authors.</comment>
	</row>
	<row>
		<name>brandy_book_v1_post_6</name>
		<title>Supporting Local Bookstores During Holidays</title>
		<content>The holiday season is a great time to support local bookstores. Many stores offer
			special promotions, holiday-themed events, and unique gift options. Shopping at
			independent bookstores not only supports local businesses but also provides you with
			one-of-a-kind gifts for book lovers in your life. Make a difference this holiday season
			by shopping locally!</content>
		<featured_image>http://img.wpbrandy.com/uploads/plants-home-gallery-img-6.png</featured_image>
		<category domain="category" nicename="Holiday Shopping"><![CDATA[Holiday Shopping]]></category>
		<category domain="category" nicename="Local Bookstores"><![CDATA[Local Bookstores]]></category>
		<category domain="category" nicename="Holiday Shopping"><![CDATA[Holiday Shopping]]></category>
		<comment>Great reminder! I always try to buy my holiday gifts from local bookstores. It’s a
			win-win: I find special gifts, and I support a great local business.</comment>
		<comment>Absolutely! The personalized recommendations and unique finds are so much better
			than what you’d get at big-box stores.</comment>
	</row>
</root>