[
  {
    "ID": 1,
    "name": "brandy_wc_homepage_elementor",
    "title": "[Elementor] WooCommerce Home Page",
    "content": "",
    "elementor_data": "[{\"id\":\"8426b34\",\"elType\":\"container\",\"settings\":{\"content_width\":\"full\",\"flex_direction\":\"row\",\"flex_justify_content\":\"center\",\"flex_align_items\":\"center\",\"flex_gap\":{\"column\":\"2\",\"row\":\"2\",\"isLinked\":false,\"unit\":\"rem\",\"size\":2},\"flex_gap_tablet\":{\"column\":\"\",\"row\":\"\",\"isLinked\":true,\"unit\":\"rem\",\"size\":null},\"flex_gap_mobile\":{\"column\":\"\",\"row\":\"\",\"isLinked\":true,\"unit\":\"rem\",\"size\":null},\"background_background\":\"classic\",\"background_color\":\"#F1F6FA\",\"margin\":{\"unit\":\"rem\",\"top\":\"0\",\"right\":\"0\",\"bottom\":\"2\",\"left\":\"0\",\"isLinked\":false},\"margin_tablet\":{\"unit\":\"rem\",\"top\":\"\",\"right\":\"\",\"bottom\":\"\",\"left\":\"\",\"isLinked\":true},\"margin_mobile\":{\"unit\":\"rem\",\"top\":\"\",\"right\":\"\",\"bottom\":\"\",\"left\":\"\",\"isLinked\":true},\"padding\":{\"unit\":\"em\",\"top\":\"1\",\"right\":\"1\",\"bottom\":\"1\",\"left\":\"1\",\"isLinked\":true},\"padding_tablet\":{\"unit\":\"em\",\"top\":\"\",\"right\":\"\",\"bottom\":\"\",\"left\":\"\",\"isLinked\":true},\"padding_mobile\":{\"unit\":\"em\",\"top\":\"\",\"right\":\"\",\"bottom\":\"\",\"left\":\"\",\"isLinked\":true}},\"elements\":[{\"id\":\"e9a975d\",\"elType\":\"container\",\"settings\":{\"content_width\":\"full\",\"width\":{\"unit\":\"custom\",\"size\":\"1500px\",\"sizes\":[]},\"width_tablet\":{\"unit\":\"custom\",\"size\":\"\",\"sizes\":[]},\"width_mobile\":{\"unit\":\"custom\",\"size\":\"\",\"sizes\":[]},\"flex_direction\":\"row\",\"flex_align_items\":\"center\",\"margin\":{\"unit\":\"px\",\"top\":\"0\",\"right\":\"0\",\"bottom\":\"0\",\"left\":\"0\",\"isLinked\":false},\"padding\":{\"unit\":\"px\",\"top\":\"0\",\"right\":\"0\",\"bottom\":\"0\",\"left\":\"0\",\"isLinked\":false}},\"elements\":[{\"id\":\"92b2473\",\"elType\":\"container\",\"settings\":{\"flex_gap\":{\"column\":\"0\",\"row\":\"0\",\"isLinked\":true,\"unit\":\"px\",\"size\":0},\"margin\":{\"unit\":\"px\",\"top\":\"0\",\"right\":\"0\",\"bottom\":\"0\",\"left\":\"0\",\"isLinked\":false},\"padding\":{\"unit\":\"px\",\"top\":\"0\",\"right\":\"0\",\"bottom\":\"0\",\"left\":\"0\",\"isLinked\":false},\"flex_align_items\":\"flex-start\"},\"elements\":[{\"id\":\"5eae6fe\",\"elType\":\"widget\",\"settings\":{\"editor\":\"<p>NEW ARRIVALS<\\/p>\",\"typography_typography\":\"custom\",\"typography_font_size\":{\"unit\":\"rem\",\"size\":1.125,\"sizes\":[]},\"typography_font_size_tablet\":{\"unit\":\"rem\",\"size\":0.875,\"sizes\":[]},\"typography_font_size_mobile\":{\"unit\":\"rem\",\"size\":\"\",\"sizes\":[]},\"typography_line_height\":{\"unit\":\"rem\",\"size\":\"\",\"sizes\":[]},\"typography_line_height_tablet\":{\"unit\":\"custom\",\"size\":\"1.25\",\"sizes\":[]},\"typography_line_height_mobile\":{\"unit\":\"custom\",\"size\":\"\",\"sizes\":[]},\"typography_letter_spacing\":{\"unit\":\"px\",\"size\":5.4,\"sizes\":[]},\"_margin\":{\"unit\":\"rem\",\"top\":\"0\",\"right\":\"0\",\"bottom\":\"1\",\"left\":\"0\",\"isLinked\":false},\"_margin_tablet\":{\"unit\":\"rem\",\"top\":\"0\",\"right\":\"0\",\"bottom\":\"0.25\",\"left\":\"0\",\"isLinked\":false},\"_margin_mobile\":{\"unit\":\"rem\",\"top\":\"\",\"right\":\"\",\"bottom\":\"\",\"left\":\"\",\"isLinked\":true}},\"elements\":[],\"widgetType\":\"text-editor\"},{\"id\":\"a96c60e\",\"elType\":\"widget\",\"settings\":{\"title\":\"Perfect Fashion For Summer\",\"typography_typography\":\"custom\",\"typography_font_size\":{\"unit\":\"px\",\"size\":70,\"sizes\":[]},\"_margin\":{\"unit\":\"rem\",\"top\":\"0\",\"right\":\"0\",\"bottom\":\"1\",\"left\":\"0\",\"isLinked\":false},\"_margin_tablet\":{\"unit\":\"rem\",\"top\":\"0\",\"right\":\"0\",\"bottom\":\"0.25\",\"left\":\"0\",\"isLinked\":false},\"_margin_mobile\":{\"unit\":\"rem\",\"top\":\"\",\"right\":\"\",\"bottom\":\"\",\"left\":\"\",\"isLinked\":true},\"typography_font_size_tablet\":{\"unit\":\"rem\",\"size\":2.25,\"sizes\":[]},\"typography_font_size_mobile\":{\"unit\":\"rem\",\"size\":\"\",\"sizes\":[]},\"typography_line_height_tablet\":{\"unit\":\"rem\",\"size\":2.5,\"sizes\":[]},\"typography_line_height_mobile\":{\"unit\":\"rem\",\"size\":\"\",\"sizes\":[]}},\"elements\":[],\"widgetType\":\"heading\"},{\"id\":\"88e7814\",\"elType\":\"widget\",\"settings\":{\"editor\":\"<p>There's nothing like a trend, let's select items to make your life with a new fashion style!<\\/p>\",\"typography_typography\":\"custom\",\"typography_font_size\":{\"unit\":\"rem\",\"size\":1.125,\"sizes\":[]},\"typography_font_size_tablet\":{\"unit\":\"rem\",\"size\":0.875,\"sizes\":[]},\"typography_font_size_mobile\":{\"unit\":\"rem\",\"size\":\"\",\"sizes\":[]},\"typography_line_height_tablet\":{\"unit\":\"custom\",\"size\":\"1.25\",\"sizes\":[]},\"typography_line_height_mobile\":{\"unit\":\"custom\",\"size\":\"\",\"sizes\":[]}},\"elements\":[],\"widgetType\":\"text-editor\"},{\"id\":\"e4a0d5e\",\"elType\":\"widget\",\"settings\":{\"text\":\"Explore Now\",\"typography_typography\":\"custom\",\"typography_font_size\":{\"unit\":\"rem\",\"size\":1.125,\"sizes\":[]},\"typography_font_size_tablet\":{\"unit\":\"rem\",\"size\":\"\",\"sizes\":[]},\"typography_font_size_mobile\":{\"unit\":\"rem\",\"size\":\"\",\"sizes\":[]},\"typography_font_weight\":\"600\",\"typography_line_height\":{\"unit\":\"custom\",\"size\":\"1.75\",\"sizes\":[]},\"typography_line_height_tablet\":{\"unit\":\"custom\",\"size\":\"\",\"sizes\":[]},\"typography_line_height_mobile\":{\"unit\":\"custom\",\"size\":\"\",\"sizes\":[]},\"text_padding\":{\"unit\":\"rem\",\"top\":\"0.75\",\"right\":\"2\",\"bottom\":\"0.75\",\"left\":\"2\",\"isLinked\":false},\"text_padding_tablet\":{\"unit\":\"rem\",\"top\":\"\",\"right\":\"\",\"bottom\":\"\",\"left\":\"\",\"isLinked\":true},\"text_padding_mobile\":{\"unit\":\"rem\",\"top\":\"\",\"right\":\"\",\"bottom\":\"\",\"left\":\"\",\"isLinked\":true},\"_margin\":{\"unit\":\"rem\",\"top\":\"2.5\",\"right\":\"0\",\"bottom\":\"0\",\"left\":\"0\",\"isLinked\":false},\"_margin_tablet\":{\"unit\":\"rem\",\"top\":\"2\",\"right\":\"0\",\"bottom\":\"0\",\"left\":\"0\",\"isLinked\":false},\"_margin_mobile\":{\"unit\":\"rem\",\"top\":\"\",\"right\":\"\",\"bottom\":\"\",\"left\":\"\",\"isLinked\":true},\"link\":{\"url\":\"https:\\/\\/yaycommerce.com\",\"is_external\":\"\",\"nofollow\":\"\",\"custom_attributes\":\"\"}},\"elements\":[],\"widgetType\":\"button\"}],\"isInner\":true},{\"id\":\"33739b9\",\"elType\":\"container\",\"settings\":{\"margin\":{\"unit\":\"px\",\"top\":\"0\",\"right\":\"0\",\"bottom\":\"0\",\"left\":\"0\",\"isLinked\":false},\"padding\":{\"unit\":\"px\",\"top\":\"0\",\"right\":\"0\",\"bottom\":\"0\",\"left\":\"0\",\"isLinked\":false}},\"elements\":[{\"id\":\"1d013fa\",\"elType\":\"widget\",\"settings\":{\"image\":{\"url\":\"http://img.wpbrandy.com/uploads/wc-about-us-banner.png\",\"id\":\"\",\"size\":\"\",\"source\":\"url\"}},\"elements\":[],\"widgetType\":\"image\"}],\"isInner\":true}],\"isInner\":true}],\"isInner\":false},{\"id\":\"607799f\",\"elType\":\"container\",\"settings\":{\"flex_direction\":\"row\",\"flex_gap\":{\"column\":\"\",\"row\":\"\",\"isLinked\":true,\"unit\":\"rem\",\"size\":null},\"flex_gap_tablet\":{\"column\":\"\",\"row\":\"\",\"isLinked\":true,\"unit\":\"rem\",\"size\":null},\"flex_gap_mobile\":{\"column\":\"\",\"row\":\"\",\"isLinked\":true,\"unit\":\"rem\",\"size\":null},\"flex_wrap_tablet\":\"wrap\",\"padding\":{\"unit\":\"px\",\"top\":\"0\",\"right\":\"0\",\"bottom\":\"0\",\"left\":\"0\",\"isLinked\":false},\"flex_wrap_mobile\":\"wrap\",\"content_width\":\"full\",\"width\":{\"unit\":\"custom\",\"size\":\"\",\"sizes\":[]},\"width_tablet\":{\"unit\":\"custom\",\"size\":\"\",\"sizes\":[]},\"width_mobile\":{\"unit\":\"custom\",\"size\":\"\",\"sizes\":[]},\"flex_justify_content\":\"center\",\"padding_tablet\":{\"unit\":\"px\",\"top\":\"0\",\"right\":\"20\",\"bottom\":\"0\",\"left\":\"20\",\"isLinked\":false}},\"elements\":[{\"id\":\"dbc884c\",\"elType\":\"container\",\"settings\":{\"content_width\":\"full\",\"width\":{\"unit\":\"custom\",\"size\":\"1500px\",\"sizes\":[]},\"width_tablet\":{\"unit\":\"custom\",\"size\":\"\",\"sizes\":[]},\"width_mobile\":{\"unit\":\"custom\",\"size\":\"\",\"sizes\":[]},\"flex_direction\":\"row\",\"flex_gap\":{\"column\":\"2\",\"row\":\"2\",\"isLinked\":true,\"unit\":\"rem\",\"size\":2},\"flex_gap_tablet\":{\"column\":\"\",\"row\":\"\",\"isLinked\":true,\"unit\":\"rem\",\"size\":null},\"flex_gap_mobile\":{\"column\":\"\",\"row\":\"\",\"isLinked\":true,\"unit\":\"rem\",\"size\":null},\"flex_wrap_tablet\":\"wrap\",\"margin\":{\"unit\":\"px\",\"top\":\"0\",\"right\":\"0\",\"bottom\":\"150\",\"left\":\"0\",\"isLinked\":false},\"margin_tablet\":{\"unit\":\"px\",\"top\":\"0\",\"right\":\"0\",\"bottom\":\"70\",\"left\":\"0\",\"isLinked\":false},\"padding\":{\"unit\":\"px\",\"top\":\"0\",\"right\":\"0\",\"bottom\":\"0\",\"left\":\"0\",\"isLinked\":false}},\"elements\":[{\"id\":\"cd8c01f\",\"elType\":\"container\",\"settings\":{\"flex_direction\":\"row\",\"flex_align_items\":\"center\",\"background_background\":\"classic\",\"background_color\":\"#EBF1F7\",\"border_radius\":{\"unit\":\"px\",\"top\":\"10\",\"right\":\"10\",\"bottom\":\"10\",\"left\":\"10\",\"isLinked\":true},\"margin\":{\"unit\":\"px\",\"top\":\"0\",\"right\":\"0\",\"bottom\":\"0\",\"left\":\"0\",\"isLinked\":false},\"padding\":{\"unit\":\"px\",\"top\":\"0\",\"right\":\"0\",\"bottom\":\"0\",\"left\":\"0\",\"isLinked\":false},\"flex_wrap_mobile\":\"nowrap\"},\"elements\":[{\"id\":\"1f67861\",\"elType\":\"container\",\"settings\":{\"flex_gap\":{\"column\":\"0\",\"row\":\"0\",\"isLinked\":true,\"unit\":\"px\",\"size\":0},\"margin\":{\"unit\":\"px\",\"top\":\"0\",\"right\":\"0\",\"bottom\":\"0\",\"left\":\"0\",\"isLinked\":false},\"padding\":{\"unit\":\"rem\",\"top\":\"2\",\"right\":\"2.5\",\"bottom\":\"2\",\"left\":\"2.5\",\"isLinked\":false},\"padding_tablet\":{\"unit\":\"rem\",\"top\":\"\",\"right\":\"\",\"bottom\":\"\",\"left\":\"\",\"isLinked\":true},\"padding_mobile\":{\"unit\":\"rem\",\"top\":\"\",\"right\":\"\",\"bottom\":\"\",\"left\":\"\",\"isLinked\":true}},\"elements\":[{\"id\":\"2a408ba\",\"elType\":\"widget\",\"settings\":{\"title\":\"The oversize favorite of all time\",\"typography_typography\":\"custom\",\"typography_font_size\":{\"unit\":\"rem\",\"size\":2.25,\"sizes\":[]},\"typography_font_size_tablet\":{\"unit\":\"px\",\"size\":21,\"sizes\":[]},\"typography_font_size_mobile\":{\"unit\":\"rem\",\"size\":\"\",\"sizes\":[]},\"typography_line_height\":{\"unit\":\"rem\",\"size\":2.5,\"sizes\":[]},\"typography_line_height_tablet\":{\"unit\":\"rem\",\"size\":\"\",\"sizes\":[]},\"typography_line_height_mobile\":{\"unit\":\"rem\",\"size\":\"\",\"sizes\":[]},\"_margin\":{\"unit\":\"rem\",\"top\":\"0\",\"right\":\"0\",\"bottom\":\"0.5\",\"left\":\"0\",\"isLinked\":false},\"_margin_tablet\":{\"unit\":\"rem\",\"top\":\"\",\"right\":\"\",\"bottom\":\"\",\"left\":\"\",\"isLinked\":true},\"_margin_mobile\":{\"unit\":\"rem\",\"top\":\"\",\"right\":\"\",\"bottom\":\"\",\"left\":\"\",\"isLinked\":true}},\"elements\":[],\"widgetType\":\"heading\"},{\"id\":\"5ad013a\",\"elType\":\"widget\",\"settings\":{\"editor\":\"<p>Take a perfect shape after experiencing our products. Let\\u2019s try it now!<\\/p>\",\"typography_typography\":\"custom\",\"hide_tablet\":\"hidden-tablet\",\"hide_mobile\":\"hidden-mobile\",\"__globals__\":{\"text_color\":\"globals\\/colors?id=brandy_body_secondary\"}},\"elements\":[],\"widgetType\":\"text-editor\"},{\"id\":\"84b82ac\",\"elType\":\"widget\",\"settings\":{\"text\":\"Shop Now\",\"typography_typography\":\"custom\",\"typography_font_size\":{\"unit\":\"rem\",\"size\":0.875,\"sizes\":[]},\"typography_font_size_tablet\":{\"unit\":\"rem\",\"size\":\"\",\"sizes\":[]},\"typography_font_size_mobile\":{\"unit\":\"rem\",\"size\":\"\",\"sizes\":[]},\"typography_font_weight\":\"600\",\"typography_line_height\":{\"unit\":\"custom\",\"size\":\"1.25\",\"sizes\":[]},\"typography_line_height_tablet\":{\"unit\":\"custom\",\"size\":\"\",\"sizes\":[]},\"typography_line_height_mobile\":{\"unit\":\"custom\",\"size\":\"\",\"sizes\":[]},\"_margin\":{\"unit\":\"rem\",\"top\":\"2\",\"right\":\"0\",\"bottom\":\"0\",\"left\":\"0\",\"isLinked\":false},\"_margin_tablet\":{\"unit\":\"rem\",\"top\":\"\",\"right\":\"\",\"bottom\":\"\",\"left\":\"\",\"isLinked\":true},\"_margin_mobile\":{\"unit\":\"rem\",\"top\":\"\",\"right\":\"\",\"bottom\":\"\",\"left\":\"\",\"isLinked\":true}},\"elements\":[],\"widgetType\":\"button\"}],\"isInner\":true},{\"id\":\"4e1f055\",\"elType\":\"widget\",\"settings\":{\"image\":{\"url\":\"http://img.wpbrandy.com/uploads/wc-campaign-banners-1.png\",\"id\":\"\",\"size\":\"\",\"source\":\"url\",\"alt\":\"\"},\"width\":{\"unit\":\"custom\",\"size\":\"218px\",\"sizes\":[]},\"width_tablet\":{\"unit\":\"custom\",\"size\":\"\",\"sizes\":[]},\"width_mobile\":{\"unit\":\"custom\",\"size\":\"\",\"sizes\":[]},\"_flex_align_self\":\"flex-end\"},\"elements\":[],\"widgetType\":\"image\"}],\"isInner\":true},{\"id\":\"a3c8fb3\",\"elType\":\"container\",\"settings\":{\"flex_direction\":\"row\",\"flex_align_items\":\"center\",\"background_background\":\"classic\",\"background_color\":\"#EBF1F7\",\"border_radius\":{\"unit\":\"px\",\"top\":\"10\",\"right\":\"10\",\"bottom\":\"10\",\"left\":\"10\",\"isLinked\":true},\"margin\":{\"unit\":\"px\",\"top\":\"0\",\"right\":\"0\",\"bottom\":\"0\",\"left\":\"0\",\"isLinked\":false},\"padding\":{\"unit\":\"px\",\"top\":\"0\",\"right\":\"0\",\"bottom\":\"0\",\"left\":\"0\",\"isLinked\":false},\"flex_wrap_mobile\":\"nowrap\"},\"elements\":[{\"id\":\"4f382ea\",\"elType\":\"container\",\"settings\":{\"flex_gap\":{\"column\":\"0\",\"row\":\"0\",\"isLinked\":true,\"unit\":\"px\",\"size\":0},\"margin\":{\"unit\":\"px\",\"top\":\"0\",\"right\":\"0\",\"bottom\":\"0\",\"left\":\"0\",\"isLinked\":false},\"padding\":{\"unit\":\"rem\",\"top\":\"2\",\"right\":\"2.5\",\"bottom\":\"2\",\"left\":\"2.5\",\"isLinked\":false},\"padding_tablet\":{\"unit\":\"rem\",\"top\":\"\",\"right\":\"\",\"bottom\":\"\",\"left\":\"\",\"isLinked\":true},\"padding_mobile\":{\"unit\":\"rem\",\"top\":\"\",\"right\":\"\",\"bottom\":\"\",\"left\":\"\",\"isLinked\":true}},\"elements\":[{\"id\":\"1f0b19e\",\"elType\":\"widget\",\"settings\":{\"title\":\"The oversize favorite of all time\",\"typography_typography\":\"custom\",\"typography_font_size\":{\"unit\":\"rem\",\"size\":2.25,\"sizes\":[]},\"typography_font_size_tablet\":{\"unit\":\"px\",\"size\":21,\"sizes\":[]},\"typography_font_size_mobile\":{\"unit\":\"rem\",\"size\":\"\",\"sizes\":[]},\"typography_line_height\":{\"unit\":\"rem\",\"size\":2.5,\"sizes\":[]},\"typography_line_height_tablet\":{\"unit\":\"rem\",\"size\":\"\",\"sizes\":[]},\"typography_line_height_mobile\":{\"unit\":\"rem\",\"size\":\"\",\"sizes\":[]},\"_margin\":{\"unit\":\"rem\",\"top\":\"0\",\"right\":\"0\",\"bottom\":\"0.5\",\"left\":\"0\",\"isLinked\":false},\"_margin_tablet\":{\"unit\":\"rem\",\"top\":\"\",\"right\":\"\",\"bottom\":\"\",\"left\":\"\",\"isLinked\":true},\"_margin_mobile\":{\"unit\":\"rem\",\"top\":\"\",\"right\":\"\",\"bottom\":\"\",\"left\":\"\",\"isLinked\":true}},\"elements\":[],\"widgetType\":\"heading\"},{\"id\":\"5e56ac1\",\"elType\":\"widget\",\"settings\":{\"editor\":\"<p>Take a perfect shape after experiencing our products. Let\\u2019s try it now!<\\/p>\",\"typography_typography\":\"custom\",\"hide_tablet\":\"hidden-tablet\",\"hide_mobile\":\"hidden-mobile\",\"__globals__\":{\"text_color\":\"globals\\/colors?id=brandy_body_secondary\"}},\"elements\":[],\"widgetType\":\"text-editor\"},{\"id\":\"c613990\",\"elType\":\"widget\",\"settings\":{\"text\":\"Shop Now\",\"typography_typography\":\"custom\",\"typography_font_size\":{\"unit\":\"rem\",\"size\":0.875,\"sizes\":[]},\"typography_font_size_tablet\":{\"unit\":\"rem\",\"size\":\"\",\"sizes\":[]},\"typography_font_size_mobile\":{\"unit\":\"rem\",\"size\":\"\",\"sizes\":[]},\"typography_font_weight\":\"600\",\"typography_line_height\":{\"unit\":\"custom\",\"size\":\"1.25\",\"sizes\":[]},\"typography_line_height_tablet\":{\"unit\":\"custom\",\"size\":\"\",\"sizes\":[]},\"typography_line_height_mobile\":{\"unit\":\"custom\",\"size\":\"\",\"sizes\":[]},\"_margin\":{\"unit\":\"rem\",\"top\":\"2\",\"right\":\"0\",\"bottom\":\"0\",\"left\":\"0\",\"isLinked\":false},\"_margin_tablet\":{\"unit\":\"rem\",\"top\":\"\",\"right\":\"\",\"bottom\":\"\",\"left\":\"\",\"isLinked\":true},\"_margin_mobile\":{\"unit\":\"rem\",\"top\":\"\",\"right\":\"\",\"bottom\":\"\",\"left\":\"\",\"isLinked\":true}},\"elements\":[],\"widgetType\":\"button\"}],\"isInner\":true},{\"id\":\"227a357\",\"elType\":\"widget\",\"settings\":{\"image\":{\"url\":\"http://img.wpbrandy.com/uploads/wc-campaign-banners-2.png\",\"id\":\"\",\"size\":\"\",\"source\":\"url\",\"alt\":\"\"},\"width\":{\"unit\":\"custom\",\"size\":\"218px\",\"sizes\":[]},\"width_tablet\":{\"unit\":\"custom\",\"size\":\"\",\"sizes\":[]},\"width_mobile\":{\"unit\":\"custom\",\"size\":\"\",\"sizes\":[]},\"_flex_align_self\":\"flex-end\"},\"elements\":[],\"widgetType\":\"image\"}],\"isInner\":true}],\"isInner\":true}],\"isInner\":false},{\"id\":\"e55f242\",\"elType\":\"container\",\"settings\":{\"flex_gap\":{\"column\":\"0\",\"row\":\"0\",\"isLinked\":true,\"unit\":\"px\",\"size\":0},\"padding\":{\"unit\":\"px\",\"top\":\"0\",\"right\":\"0\",\"bottom\":\"0\",\"left\":\"0\",\"isLinked\":true},\"margin_tablet\":{\"unit\":\"px\",\"top\":\"0\",\"right\":\"0\",\"bottom\":\"70\",\"left\":\"0\",\"isLinked\":false},\"content_width\":\"full\",\"width\":{\"unit\":\"custom\",\"size\":\"\",\"sizes\":[]},\"width_tablet\":{\"unit\":\"custom\",\"size\":\"\",\"sizes\":[]},\"width_mobile\":{\"unit\":\"custom\",\"size\":\"\",\"sizes\":[]},\"flex_direction\":\"row\",\"flex_justify_content\":\"center\",\"padding_tablet\":{\"unit\":\"px\",\"top\":\"0\",\"right\":\"20\",\"bottom\":\"0\",\"left\":\"20\",\"isLinked\":false},\"css_classes\":\"builder-boxed\"},\"elements\":[{\"id\":\"8dc3d02\",\"elType\":\"container\",\"settings\":{\"content_width\":\"full\",\"width\":{\"unit\":\"custom\",\"size\":\"1500px\",\"sizes\":[]},\"width_tablet\":{\"unit\":\"custom\",\"size\":\"\",\"sizes\":[]},\"width_mobile\":{\"unit\":\"custom\",\"size\":\"\",\"sizes\":[]},\"flex_gap\":{\"column\":\"0\",\"row\":\"0\",\"isLinked\":true,\"unit\":\"px\",\"size\":0},\"margin\":{\"unit\":\"px\",\"top\":\"0\",\"right\":\"0\",\"bottom\":\"150\",\"left\":\"0\",\"isLinked\":false},\"margin_tablet\":{\"unit\":\"px\",\"top\":\"0\",\"right\":\"0\",\"bottom\":\"70\",\"left\":\"0\",\"isLinked\":false},\"padding\":{\"unit\":\"px\",\"top\":\"0\",\"right\":\"0\",\"bottom\":\"0\",\"left\":\"0\",\"isLinked\":false}},\"elements\":[{\"id\":\"9e76cdb\",\"elType\":\"widget\",\"settings\":{\"title\":\"Discover our featured products\",\"align\":\"center\",\"align_tablet\":\"center\",\"typography_typography\":\"custom\",\"typography_font_size\":{\"unit\":\"rem\",\"size\":2.25,\"sizes\":[]},\"typography_font_size_tablet\":{\"unit\":\"px\",\"size\":28,\"sizes\":[]},\"typography_font_size_mobile\":{\"unit\":\"rem\",\"size\":\"\",\"sizes\":[]},\"typography_line_height\":{\"unit\":\"rem\",\"size\":\"\",\"sizes\":[]},\"typography_line_height_tablet\":{\"unit\":\"custom\",\"size\":\"\",\"sizes\":[]},\"typography_line_height_mobile\":{\"unit\":\"custom\",\"size\":\"\",\"sizes\":[]},\"_margin_tablet\":{\"unit\":\"rem\",\"top\":\"0\",\"right\":\"0\",\"bottom\":\"1.25\",\"left\":\"0\",\"isLinked\":false},\"_padding_tablet\":{\"unit\":\"px\",\"top\":\"0\",\"right\":\"0\",\"bottom\":\"0\",\"left\":\"0\",\"isLinked\":false},\"_margin\":{\"unit\":\"rem\",\"top\":\"0\",\"right\":\"0\",\"bottom\":\"2.5\",\"left\":\"0\",\"isLinked\":false},\"_margin_mobile\":{\"unit\":\"rem\",\"top\":\"\",\"right\":\"\",\"bottom\":\"\",\"left\":\"\",\"isLinked\":true},\"_padding\":{\"unit\":\"px\",\"top\":\"0\",\"right\":\"0\",\"bottom\":\"0\",\"left\":\"0\",\"isLinked\":false}},\"elements\":[],\"widgetType\":\"heading\"},{\"id\":\"605bc0e\",\"elType\":\"widget\",\"settings\":{\"products_related_products_title_text\":\"Related Products\",\"products_upsells_title_text\":\"You may also like...\",\"products_cross_sells_title_text\":\"You may be interested in...\",\"rows\":1},\"elements\":[],\"widgetType\":\"woocommerce-products\"}],\"isInner\":true}],\"isInner\":false},{\"id\":\"d009d05\",\"elType\":\"container\",\"settings\":{\"background_background\":\"classic\",\"padding\":{\"unit\":\"px\",\"top\":\"0\",\"right\":\"0\",\"bottom\":\"0\",\"left\":\"0\",\"isLinked\":false},\"content_width\":\"full\",\"width\":{\"unit\":\"custom\",\"size\":\"\",\"sizes\":[]},\"width_tablet\":{\"unit\":\"%\",\"size\":\"\",\"sizes\":[]},\"width_mobile\":{\"unit\":\"custom\",\"size\":\"\",\"sizes\":[]},\"flex_direction\":\"row\",\"flex_justify_content\":\"center\",\"css_classes\":\"builder-boxed\"},\"elements\":[{\"id\":\"13436f4\",\"elType\":\"container\",\"settings\":{\"content_width\":\"full\",\"width\":{\"unit\":\"custom\",\"size\":\"1500px\",\"sizes\":[]},\"width_tablet\":{\"unit\":\"%\",\"size\":100,\"sizes\":[]},\"width_mobile\":{\"unit\":\"custom\",\"size\":\"\",\"sizes\":[]},\"margin\":{\"unit\":\"px\",\"top\":\"0\",\"right\":\"0\",\"bottom\":\"150\",\"left\":\"0\",\"isLinked\":false},\"margin_tablet\":{\"unit\":\"px\",\"top\":\"0\",\"right\":\"0\",\"bottom\":\"70\",\"left\":\"0\",\"isLinked\":false},\"padding\":{\"unit\":\"px\",\"top\":\"0\",\"right\":\"0\",\"bottom\":\"0\",\"left\":\"0\",\"isLinked\":false}},\"elements\":[{\"id\":\"ae8c56b\",\"elType\":\"widget\",\"settings\":{\"testimonial_content\":\"Making a type specimen book, also the leap into electronic typesetting, remain essentially unchanged or avoids pleasure itself the master builder of lorem ipsum amet quist human happiness.\",\"testimonial_name\":\"Lyly Carley\",\"testimonial_job\":\"Designer\",\"testimonial_image\":{\"url\":\"http://img.wpbrandy.com/uploads/testimonial-avatar.png\",\"id\":\"\",\"size\":\"\",\"source\":\"url\",\"alt\":\"\"},\"testimonial_image_position\":\"top\",\"content_typography_typography\":\"custom\",\"content_typography_font_size\":{\"unit\":\"rem\",\"size\":2.25,\"sizes\":[]},\"content_typography_font_size_tablet\":{\"unit\":\"rem\",\"size\":2,\"sizes\":[]},\"content_typography_font_size_mobile\":{\"unit\":\"px\",\"size\":21,\"sizes\":[]},\"image_size\":{\"unit\":\"px\",\"size\":60,\"sizes\":[]},\"image_border_border\":\"none\",\"image_border_radius\":{\"unit\":\"px\",\"top\":\"50\",\"right\":\"50\",\"bottom\":\"50\",\"left\":\"50\",\"isLinked\":true},\"name_typography_typography\":\"custom\",\"name_typography_font_size\":{\"unit\":\"rem\",\"size\":1.125,\"sizes\":[]},\"name_typography_font_size_tablet\":{\"unit\":\"rem\",\"size\":\"\",\"sizes\":[]},\"name_typography_font_size_mobile\":{\"unit\":\"rem\",\"size\":\"\",\"sizes\":[]},\"name_typography_font_weight\":\"500\",\"name_typography_line_height\":{\"unit\":\"custom\",\"size\":\"1\",\"sizes\":[]},\"name_typography_line_height_tablet\":{\"unit\":\"custom\",\"size\":\"\",\"sizes\":[]},\"name_typography_line_height_mobile\":{\"unit\":\"custom\",\"size\":\"\",\"sizes\":[]},\"job_typography_typography\":\"custom\",\"job_typography_line_height\":{\"unit\":\"px\",\"size\":36,\"sizes\":[]},\"_padding\":{\"unit\":\"rem\",\"top\":\"4\",\"right\":\"9\",\"bottom\":\"4\",\"left\":\"9\",\"isLinked\":false},\"_padding_tablet\":{\"unit\":\"rem\",\"top\":\"2\",\"right\":\"4\",\"bottom\":\"2\",\"left\":\"4\",\"isLinked\":false},\"_padding_mobile\":{\"unit\":\"rem\",\"top\":\"1\",\"right\":\"1\",\"bottom\":\"1\",\"left\":\"1\",\"isLinked\":true},\"_background_background\":\"classic\",\"_background_color\":\"#F9FAFC\",\"_border_radius\":{\"unit\":\"px\",\"top\":\"15\",\"right\":\"15\",\"bottom\":\"15\",\"left\":\"15\",\"isLinked\":true},\"__globals__\":{\"job_text_color\":\"globals\\/colors?id=brandy_body_secondary\"},\"_element_width\":\"inherit\",\"_element_width_tablet\":\"initial\",\"_element_custom_width\":{\"unit\":\"custom\",\"size\":\"\",\"sizes\":[]},\"_element_custom_width_tablet\":{\"unit\":\"%\",\"size\":\"\",\"sizes\":[]},\"_element_custom_width_mobile\":{\"unit\":\"custom\",\"size\":\"\",\"sizes\":[]}},\"elements\":[],\"widgetType\":\"testimonial\"}],\"isInner\":true}],\"isInner\":false},{\"id\":\"a6fa937\",\"elType\":\"container\",\"settings\":{\"flex_gap_tablet\":{\"column\":\"0\",\"row\":\"0\",\"isLinked\":true,\"unit\":\"px\",\"size\":0},\"margin_tablet\":{\"unit\":\"px\",\"top\":\"0\",\"right\":\"0\",\"bottom\":\"70\",\"left\":\"0\",\"isLinked\":false},\"padding\":{\"unit\":\"px\",\"top\":\"0\",\"right\":\"0\",\"bottom\":\"0\",\"left\":\"0\",\"isLinked\":false},\"content_width\":\"full\",\"width\":{\"unit\":\"custom\",\"size\":\"\",\"sizes\":[]},\"width_tablet\":{\"unit\":\"custom\",\"size\":\"\",\"sizes\":[]},\"width_mobile\":{\"unit\":\"custom\",\"size\":\"\",\"sizes\":[]},\"flex_direction\":\"row\",\"flex_justify_content\":\"center\",\"css_classes\":\"builder-boxed\"},\"elements\":[{\"id\":\"36fcd99\",\"elType\":\"container\",\"settings\":{\"content_width\":\"full\",\"width\":{\"unit\":\"custom\",\"size\":\"1500px\",\"sizes\":[]},\"width_tablet\":{\"unit\":\"custom\",\"size\":\"\",\"sizes\":[]},\"width_mobile\":{\"unit\":\"custom\",\"size\":\"\",\"sizes\":[]},\"flex_gap\":{\"column\":\"0\",\"row\":\"0\",\"isLinked\":true,\"unit\":\"px\",\"size\":0},\"margin\":{\"unit\":\"px\",\"top\":\"0\",\"right\":\"0\",\"bottom\":\"150\",\"left\":\"0\",\"isLinked\":false},\"margin_tablet\":{\"unit\":\"px\",\"top\":\"0\",\"right\":\"0\",\"bottom\":\"70\",\"left\":\"0\",\"isLinked\":false},\"padding\":{\"unit\":\"px\",\"top\":\"0\",\"right\":\"0\",\"bottom\":\"0\",\"left\":\"0\",\"isLinked\":false}},\"elements\":[{\"id\":\"9d1e191\",\"elType\":\"widget\",\"settings\":{\"title\":\"The most searched products\",\"align\":\"center\",\"typography_typography\":\"custom\",\"typography_font_size\":{\"unit\":\"rem\",\"size\":2.25,\"sizes\":[]},\"typography_font_size_tablet\":{\"unit\":\"px\",\"size\":28,\"sizes\":[]},\"typography_font_size_mobile\":{\"unit\":\"rem\",\"size\":\"\",\"sizes\":[]},\"typography_line_height\":{\"unit\":\"rem\",\"size\":\"\",\"sizes\":[]},\"typography_line_height_tablet\":{\"unit\":\"custom\",\"size\":\"\",\"sizes\":[]},\"typography_line_height_mobile\":{\"unit\":\"custom\",\"size\":\"\",\"sizes\":[]},\"_margin\":{\"unit\":\"rem\",\"top\":\"0\",\"right\":\"0\",\"bottom\":\"2.5\",\"left\":\"0\",\"isLinked\":false},\"_margin_tablet\":{\"unit\":\"rem\",\"top\":\"0\",\"right\":\"0\",\"bottom\":\"1.25\",\"left\":\"0\",\"isLinked\":false},\"_margin_mobile\":{\"unit\":\"rem\",\"top\":\"\",\"right\":\"\",\"bottom\":\"\",\"left\":\"\",\"isLinked\":true},\"_padding\":{\"unit\":\"px\",\"top\":\"0\",\"right\":\"0\",\"bottom\":\"0\",\"left\":\"0\",\"isLinked\":false}},\"elements\":[],\"widgetType\":\"heading\"},{\"id\":\"6e3b758\",\"elType\":\"widget\",\"settings\":{\"products_related_products_title_text\":\"Related Products\",\"products_upsells_title_text\":\"You may also like...\",\"products_cross_sells_title_text\":\"You may be interested in...\"},\"elements\":[],\"widgetType\":\"woocommerce-products\"}],\"isInner\":true}],\"isInner\":false},{\"id\":\"215981e\",\"elType\":\"container\",\"settings\":{\"flex_gap\":{\"column\":\"0\",\"row\":\"0\",\"isLinked\":true,\"unit\":\"px\",\"size\":0},\"margin_tablet\":{\"unit\":\"px\",\"top\":\"0\",\"right\":\"0\",\"bottom\":\"70\",\"left\":\"0\",\"isLinked\":false},\"padding\":{\"unit\":\"px\",\"top\":\"0\",\"right\":\"0\",\"bottom\":\"0\",\"left\":\"0\",\"isLinked\":true},\"content_width\":\"full\",\"width\":{\"unit\":\"custom\",\"size\":\"\",\"sizes\":[]},\"width_tablet\":{\"unit\":\"custom\",\"size\":\"\",\"sizes\":[]},\"width_mobile\":{\"unit\":\"custom\",\"size\":\"\",\"sizes\":[]},\"flex_direction\":\"row\",\"flex_justify_content\":\"center\",\"css_classes\":\"builder-boxed\"},\"elements\":[{\"id\":\"4e8fabc\",\"elType\":\"container\",\"settings\":{\"content_width\":\"full\",\"width\":{\"unit\":\"custom\",\"size\":\"1500px\",\"sizes\":[]},\"width_tablet\":{\"unit\":\"custom\",\"size\":\"\",\"sizes\":[]},\"width_mobile\":{\"unit\":\"custom\",\"size\":\"\",\"sizes\":[]},\"flex_gap\":{\"column\":\"0\",\"row\":\"0\",\"isLinked\":true,\"unit\":\"px\",\"size\":0},\"margin\":{\"unit\":\"px\",\"top\":\"0\",\"right\":\"0\",\"bottom\":\"150\",\"left\":\"0\",\"isLinked\":false},\"margin_tablet\":{\"unit\":\"px\",\"top\":\"0\",\"right\":\"0\",\"bottom\":\"70\",\"left\":\"0\",\"isLinked\":false},\"padding\":{\"unit\":\"px\",\"top\":\"0\",\"right\":\"0\",\"bottom\":\"0\",\"left\":\"0\",\"isLinked\":false}},\"elements\":[{\"id\":\"be1b050\",\"elType\":\"widget\",\"settings\":{\"title\":\"Our blog make life richer\",\"align\":\"center\",\"typography_typography\":\"custom\",\"typography_font_size_tablet\":{\"unit\":\"px\",\"size\":28,\"sizes\":[]},\"_margin\":{\"unit\":\"rem\",\"top\":\"0\",\"right\":\"0\",\"bottom\":\"2.5\",\"left\":\"0\",\"isLinked\":false},\"_margin_tablet\":{\"unit\":\"rem\",\"top\":\"0\",\"right\":\"0\",\"bottom\":\"1.25\",\"left\":\"0\",\"isLinked\":false},\"_margin_mobile\":{\"unit\":\"rem\",\"top\":\"\",\"right\":\"\",\"bottom\":\"\",\"left\":\"\",\"isLinked\":true},\"_padding\":{\"unit\":\"px\",\"top\":\"0\",\"right\":\"0\",\"bottom\":\"0\",\"left\":\"0\",\"isLinked\":false}},\"elements\":[],\"widgetType\":\"heading\"},{\"id\":\"3051d6d\",\"elType\":\"widget\",\"settings\":{\"classic_posts_per_page\":3,\"classic_thumbnail_size_size\":\"large\",\"classic_show_excerpt\":\"\",\"classic_meta_data\":[\"date\"],\"classic_meta_separator\":\"\\/\\/\\/\",\"classic_show_read_more\":\"\",\"classic_read_more_text\":\"Read More \\u00bb\",\"cards_meta_separator\":\"\\u2022\",\"cards_read_more_text\":\"Read More \\u00bb\",\"full_content_meta_separator\":\"\\/\\/\\/\",\"classic_column_gap\":{\"unit\":\"rem\",\"size\":2,\"sizes\":[]},\"classic_column_gap_tablet\":{\"unit\":\"rem\",\"size\":\"\",\"sizes\":[]},\"classic_column_gap_mobile\":{\"unit\":\"rem\",\"size\":\"\",\"sizes\":[]},\"classic_row_gap\":{\"unit\":\"rem\",\"size\":2,\"sizes\":[]},\"classic_row_gap_tablet\":{\"unit\":\"rem\",\"size\":\"\",\"sizes\":[]},\"classic_row_gap_mobile\":{\"unit\":\"rem\",\"size\":\"\",\"sizes\":[]},\"classic_alignment\":\"center\",\"classic_img_border_radius\":{\"unit\":\"px\",\"top\":\"10\",\"right\":\"10\",\"bottom\":\"10\",\"left\":\"10\",\"isLinked\":true},\"classic_title_typography_typography\":\"custom\",\"classic_title_typography_font_size\":{\"unit\":\"rem\",\"size\":1.125,\"sizes\":[]},\"classic_title_typography_font_size_tablet\":{\"unit\":\"rem\",\"size\":\"\",\"sizes\":[]},\"classic_title_typography_font_size_mobile\":{\"unit\":\"rem\",\"size\":\"\",\"sizes\":[]},\"classic_text_stroke_text_stroke_type\":\"yes\",\"classic_text_stroke_text_stroke\":{\"unit\":\"px\",\"size\":0,\"sizes\":[]},\"classic_title_spacing\":{\"unit\":\"px\",\"size\":10,\"sizes\":[]},\"classic_meta_typography_typography\":\"custom\",\"classic_meta_typography_font_size\":{\"unit\":\"rem\",\"size\":0.875,\"sizes\":[]},\"classic_meta_typography_font_size_tablet\":{\"unit\":\"rem\",\"size\":\"\",\"sizes\":[]},\"classic_meta_typography_font_size_mobile\":{\"unit\":\"rem\",\"size\":\"\",\"sizes\":[]},\"pagination_page_limit\":\"5\",\"pagination_prev_label\":\"&laquo; Previous\",\"pagination_next_label\":\"Next &raquo;\",\"text\":\"Load More\",\"load_more_no_posts_custom_message\":\"No more posts to show\",\"__globals__\":{\"classic_title_color\":\"globals\\/colors?id=brandy_body_primary\",\"classic_meta_color\":\"globals\\/colors?id=brandy_body_secondary\"}},\"elements\":[],\"widgetType\":\"posts\"}],\"isInner\":true}],\"isInner\":false}]",
    "page_display": "front_page"
  },
  {
    "ID": 2,
    "name": "brandy_blog",
    "title": "[Elementor] Brandy Blog",
    "content": "",
    "elementor_data": "",
    "page_display": "blogs_page"
  },
  {
    "ID": 3,
    "name": "brandy_wc_about_us_elementor",
    "title": "[Elementor] WooCommerce About Us",
    "content": "",
    "elementor_data": "[{\"id\":\"3c0b31c\",\"elType\":\"container\",\"settings\":{\"content_width\":\"full\",\"margin\":{\"unit\":\"px\",\"top\":\"0\",\"right\":\"0\",\"bottom\":\"150\",\"left\":\"0\",\"isLinked\":false},\"padding\":{\"unit\":\"px\",\"top\":\"0\",\"right\":\"0\",\"bottom\":\"0\",\"left\":\"0\",\"isLinked\":false},\"margin_tablet\":{\"unit\":\"px\",\"top\":\"0\",\"right\":\"0\",\"bottom\":\"70\",\"left\":\"0\",\"isLinked\":false}},\"elements\":[{\"id\":\"13307a7\",\"elType\":\"container\",\"settings\":{\"content_width\":\"full\",\"flex_direction\":\"row\",\"flex_align_items\":\"center\",\"flex_gap\":{\"column\":\"50\",\"row\":\"50\",\"isLinked\":true,\"unit\":\"px\",\"size\":50},\"grid_columns_grid\":{\"unit\":\"fr\",\"size\":9,\"sizes\":[]},\"padding\":{\"unit\":\"px\",\"top\":\"0\",\"right\":\"0\",\"bottom\":\"0\",\"left\":\"0\",\"isLinked\":false},\"css_classes\":\"builder-boxed\",\"presetTitle\":\"Container\",\"presetIcon\":\"eicon-container\"},\"elements\":[{\"id\":\"5b5ac34\",\"elType\":\"container\",\"settings\":{\"content_width\":\"full\",\"width\":{\"unit\":\"%\",\"size\":54.366},\"width_tablet\":{\"unit\":\"%\",\"size\":\"\",\"sizes\":[]},\"width_mobile\":{\"unit\":\"%\",\"size\":\"\",\"sizes\":[]},\"flex_gap\":{\"column\":\"0\",\"row\":\"0\",\"isLinked\":true,\"unit\":\"px\",\"size\":0},\"padding\":{\"unit\":\"px\",\"top\":\"0\",\"right\":\"0\",\"bottom\":\"0\",\"left\":\"0\",\"isLinked\":false},\"_flex_size\":\"none\",\"_element_width\":\"initial\"},\"elements\":[{\"id\":\"bf2b84f\",\"elType\":\"widget\",\"settings\":{\"title\":\"The Place for Creativity Minimalism\",\"typography_typography\":\"custom\",\"typography_font_size\":{\"unit\":\"rem\",\"size\":2.25,\"sizes\":[]},\"typography_font_size_tablet\":{\"unit\":\"rem\",\"size\":2,\"sizes\":[]},\"typography_font_size_mobile\":{\"unit\":\"rem\",\"size\":\"\",\"sizes\":[]},\"typography_font_weight\":\"600\",\"typography_line_height\":{\"unit\":\"custom\",\"size\":\"1.175\",\"sizes\":[]},\"typography_line_height_tablet\":{\"unit\":\"custom\",\"size\":\"\",\"sizes\":[]},\"typography_line_height_mobile\":{\"unit\":\"custom\",\"size\":\"\",\"sizes\":[]},\"_margin\":{\"unit\":\"rem\",\"top\":\"0\",\"right\":\"0\",\"bottom\":\"2\",\"left\":\"0\",\"isLinked\":false},\"_margin_tablet\":{\"unit\":\"rem\",\"top\":\"\",\"right\":\"\",\"bottom\":\"\",\"left\":\"\",\"isLinked\":true},\"_margin_mobile\":{\"unit\":\"rem\",\"top\":\"\",\"right\":\"\",\"bottom\":\"\",\"left\":\"\",\"isLinked\":true}},\"elements\":[],\"widgetType\":\"heading\"},{\"id\":\"2365cca\",\"elType\":\"widget\",\"settings\":{\"editor\":\"<p>Whether you\\u2019re more of a casual girl I feeling you, give me joggers all day every day or are looking to spice things up for your next date night.<\\/p>\",\"_margin\":{\"unit\":\"rem\",\"top\":\"0\",\"right\":\"0\",\"bottom\":\"1\",\"left\":\"0\",\"isLinked\":false},\"_margin_tablet\":{\"unit\":\"rem\",\"top\":\"\",\"right\":\"\",\"bottom\":\"\",\"left\":\"\",\"isLinked\":true},\"_margin_mobile\":{\"unit\":\"rem\",\"top\":\"\",\"right\":\"\",\"bottom\":\"\",\"left\":\"\",\"isLinked\":true}},\"elements\":[],\"widgetType\":\"text-editor\"},{\"id\":\"ee0c5e1\",\"elType\":\"widget\",\"settings\":{\"editor\":\"<p>We have been designing and producing our products in New York since 2012. We put all our passion into our craft and don\\u2019t think about stopping. That is why we own have many unique products with a minimalist style.<\\/p>\"},\"elements\":[],\"widgetType\":\"text-editor\"},{\"id\":\"dd6fb4e\",\"elType\":\"widget\",\"settings\":{\"text\":\"Explore our Products\",\"typography_typography\":\"custom\",\"typography_font_size\":{\"unit\":\"rem\",\"size\":1.125,\"sizes\":[]},\"typography_font_size_tablet\":{\"unit\":\"rem\",\"size\":\"\",\"sizes\":[]},\"typography_font_size_mobile\":{\"unit\":\"rem\",\"size\":\"\",\"sizes\":[]},\"typography_font_weight\":\"600\",\"typography_line_height\":{\"unit\":\"custom\",\"size\":\"1.75\",\"sizes\":[]},\"typography_line_height_tablet\":{\"unit\":\"custom\",\"size\":\"\",\"sizes\":[]},\"typography_line_height_mobile\":{\"unit\":\"custom\",\"size\":\"\",\"sizes\":[]},\"_margin\":{\"unit\":\"rem\",\"top\":\"2\",\"right\":\"0\",\"bottom\":\"0\",\"left\":\"0\",\"isLinked\":false},\"_margin_tablet\":{\"unit\":\"rem\",\"top\":\"\",\"right\":\"\",\"bottom\":\"\",\"left\":\"\",\"isLinked\":true},\"_margin_mobile\":{\"unit\":\"rem\",\"top\":\"\",\"right\":\"\",\"bottom\":\"\",\"left\":\"\",\"isLinked\":true}},\"elements\":[],\"widgetType\":\"button\"}],\"isInner\":true},{\"id\":\"d69fdfd\",\"elType\":\"container\",\"settings\":{\"content_width\":\"full\",\"width\":{\"unit\":\"%\",\"size\":65,\"sizes\":[]},\"padding\":{\"unit\":\"px\",\"top\":\"0\",\"right\":\"0\",\"bottom\":\"0\",\"left\":\"0\",\"isLinked\":false}},\"elements\":[{\"id\":\"98d7c5d\",\"elType\":\"widget\",\"settings\":{\"image\":{\"url\":\"http://img.wpbrandy.com/uploads/wc-about-us-banner.png\",\"id\":\"\",\"size\":\"\",\"source\":\"url\",\"alt\":\"\"}},\"elements\":[],\"widgetType\":\"image\"}],\"isInner\":true}],\"isInner\":true}],\"isInner\":false},{\"id\":\"8ba70de\",\"elType\":\"container\",\"settings\":{\"content_width\":\"full\",\"margin\":{\"unit\":\"px\",\"top\":\"0\",\"right\":\"0\",\"bottom\":\"150\",\"left\":\"0\",\"isLinked\":false},\"padding\":{\"unit\":\"px\",\"top\":\"0\",\"right\":\"0\",\"bottom\":\"0\",\"left\":\"0\",\"isLinked\":false},\"margin_tablet\":{\"unit\":\"px\",\"top\":\"0\",\"right\":\"0\",\"bottom\":\"70\",\"left\":\"0\",\"isLinked\":false}},\"elements\":[{\"id\":\"bdb65cb\",\"elType\":\"container\",\"settings\":{\"content_width\":\"full\",\"flex_direction\":\"column\",\"flex_align_items\":\"center\",\"flex_gap\":{\"column\":\"2\",\"row\":\"2\",\"isLinked\":true,\"unit\":\"rem\",\"size\":2},\"grid_columns_grid\":{\"unit\":\"fr\",\"size\":9,\"sizes\":[]},\"padding\":{\"unit\":\"px\",\"top\":\"0\",\"right\":\"0\",\"bottom\":\"0\",\"left\":\"0\",\"isLinked\":false},\"css_classes\":\"builder-boxed\",\"presetTitle\":\"Container\",\"presetIcon\":\"eicon-container\",\"flex_gap_tablet\":{\"column\":\"\",\"row\":\"\",\"isLinked\":true,\"unit\":\"rem\",\"size\":null},\"flex_gap_mobile\":{\"column\":\"\",\"row\":\"\",\"isLinked\":true,\"unit\":\"rem\",\"size\":null}},\"elements\":[{\"id\":\"d024314\",\"elType\":\"widget\",\"settings\":{\"title\":\"We get it. Getting dressed can be hard and we have everything to bring a fashion minimalism revolution for your life.\",\"align\":\"center\",\"typography_typography\":\"custom\",\"typography_font_size\":{\"unit\":\"rem\",\"size\":2.25,\"sizes\":[]},\"typography_font_size_tablet\":{\"unit\":\"rem\",\"size\":2,\"sizes\":[]},\"typography_font_size_mobile\":{\"unit\":\"rem\",\"size\":\"\",\"sizes\":[]},\"typography_line_height\":{\"unit\":\"custom\",\"size\":\"1.33\",\"sizes\":[]},\"typography_line_height_tablet\":{\"unit\":\"custom\",\"size\":\"\",\"sizes\":[]},\"typography_line_height_mobile\":{\"unit\":\"custom\",\"size\":\"\",\"sizes\":[]}},\"elements\":[],\"widgetType\":\"heading\"},{\"id\":\"12b7726\",\"elType\":\"container\",\"settings\":{\"flex_direction\":\"row\",\"flex_justify_content\":\"space-around\",\"flex_wrap_tablet\":\"wrap\",\"padding\":{\"unit\":\"px\",\"top\":\"0\",\"right\":\"0\",\"bottom\":\"0\",\"left\":\"0\",\"isLinked\":false}},\"elements\":[{\"id\":\"737adf2\",\"elType\":\"container\",\"settings\":{\"flex_gap\":{\"column\":\"0\",\"row\":\"0\",\"isLinked\":true,\"unit\":\"px\",\"size\":0},\"content_width\":\"full\",\"padding\":{\"unit\":\"px\",\"top\":\"0\",\"right\":\"0\",\"bottom\":\"0\",\"left\":\"0\",\"isLinked\":false}},\"elements\":[{\"id\":\"8616713\",\"elType\":\"widget\",\"settings\":{\"title\":\"20.5K\",\"align\":\"center\",\"typography_typography\":\"custom\",\"typography_font_size\":{\"unit\":\"px\",\"size\":70,\"sizes\":[]},\"typography_font_size_tablet\":{\"unit\":\"rem\",\"size\":2.5,\"sizes\":[]},\"typography_font_size_mobile\":{\"unit\":\"rem\",\"size\":\"\",\"sizes\":[]},\"__globals__\":{\"title_color\":\"globals\\/colors?id=brandy_accent\"}},\"elements\":[],\"widgetType\":\"heading\"},{\"id\":\"57374fd\",\"elType\":\"widget\",\"settings\":{\"editor\":\"<p>HAPPY CLIENTS<\\/p>\",\"align\":\"center\",\"__globals__\":{\"text_color\":\"globals\\/colors?id=brandy_body_secondary\"}},\"elements\":[],\"widgetType\":\"text-editor\"}],\"isInner\":true},{\"id\":\"101b092\",\"elType\":\"container\",\"settings\":{\"flex_gap\":{\"column\":\"0\",\"row\":\"0\",\"isLinked\":true,\"unit\":\"px\",\"size\":0},\"content_width\":\"full\",\"padding\":{\"unit\":\"px\",\"top\":\"0\",\"right\":\"0\",\"bottom\":\"0\",\"left\":\"0\",\"isLinked\":false}},\"elements\":[{\"id\":\"43d31c9\",\"elType\":\"widget\",\"settings\":{\"title\":\"10+\",\"align\":\"center\",\"typography_typography\":\"custom\",\"typography_font_size\":{\"unit\":\"px\",\"size\":70,\"sizes\":[]},\"typography_font_size_tablet\":{\"unit\":\"rem\",\"size\":2.5,\"sizes\":[]},\"typography_font_size_mobile\":{\"unit\":\"rem\",\"size\":\"\",\"sizes\":[]},\"__globals__\":{\"title_color\":\"globals\\/colors?id=brandy_accent\"}},\"elements\":[],\"widgetType\":\"heading\"},{\"id\":\"c427ed2\",\"elType\":\"widget\",\"settings\":{\"editor\":\"<p>YEARS BUSINESS<\\/p>\",\"align\":\"center\",\"__globals__\":{\"text_color\":\"globals\\/colors?id=brandy_body_secondary\"}},\"elements\":[],\"widgetType\":\"text-editor\"}],\"isInner\":true},{\"id\":\"679d2fd\",\"elType\":\"container\",\"settings\":{\"flex_gap\":{\"column\":\"0\",\"row\":\"0\",\"isLinked\":true,\"unit\":\"px\",\"size\":0},\"content_width\":\"full\",\"padding\":{\"unit\":\"px\",\"top\":\"0\",\"right\":\"0\",\"bottom\":\"0\",\"left\":\"0\",\"isLinked\":false}},\"elements\":[{\"id\":\"eda7907\",\"elType\":\"widget\",\"settings\":{\"title\":\"34.9M\",\"align\":\"center\",\"typography_typography\":\"custom\",\"typography_font_size\":{\"unit\":\"px\",\"size\":70,\"sizes\":[]},\"typography_font_size_tablet\":{\"unit\":\"rem\",\"size\":2.5,\"sizes\":[]},\"typography_font_size_mobile\":{\"unit\":\"rem\",\"size\":\"\",\"sizes\":[]},\"__globals__\":{\"title_color\":\"globals\\/colors?id=brandy_accent\"}},\"elements\":[],\"widgetType\":\"heading\"},{\"id\":\"545c81b\",\"elType\":\"widget\",\"settings\":{\"editor\":\"<p>PRODUCTS SOLD<\\/p>\",\"align\":\"center\",\"__globals__\":{\"text_color\":\"globals\\/colors?id=brandy_body_secondary\"}},\"elements\":[],\"widgetType\":\"text-editor\"}],\"isInner\":true},{\"id\":\"fc665b4\",\"elType\":\"container\",\"settings\":{\"flex_gap\":{\"column\":\"0\",\"row\":\"0\",\"isLinked\":true,\"unit\":\"px\",\"size\":0},\"content_width\":\"full\",\"padding\":{\"unit\":\"px\",\"top\":\"0\",\"right\":\"0\",\"bottom\":\"0\",\"left\":\"0\",\"isLinked\":false}},\"elements\":[{\"id\":\"364524a\",\"elType\":\"widget\",\"settings\":{\"title\":\"50+\",\"align\":\"center\",\"typography_typography\":\"custom\",\"typography_font_size\":{\"unit\":\"px\",\"size\":70,\"sizes\":[]},\"typography_font_size_tablet\":{\"unit\":\"rem\",\"size\":2.5,\"sizes\":[]},\"typography_font_size_mobile\":{\"unit\":\"rem\",\"size\":\"\",\"sizes\":[]},\"__globals__\":{\"title_color\":\"globals\\/colors?id=brandy_accent\"}},\"elements\":[],\"widgetType\":\"heading\"},{\"id\":\"3d8095e\",\"elType\":\"widget\",\"settings\":{\"editor\":\"<p>TEAM MEMBERS<\\/p>\",\"align\":\"center\",\"__globals__\":{\"text_color\":\"globals\\/colors?id=brandy_body_secondary\"}},\"elements\":[],\"widgetType\":\"text-editor\"}],\"isInner\":true}],\"isInner\":true}],\"isInner\":true}],\"isInner\":false},{\"id\":\"ae37a34\",\"elType\":\"container\",\"settings\":{\"content_width\":\"full\",\"margin\":{\"unit\":\"px\",\"top\":\"0\",\"right\":\"0\",\"bottom\":\"150\",\"left\":\"0\",\"isLinked\":false},\"padding\":{\"unit\":\"px\",\"top\":\"0\",\"right\":\"0\",\"bottom\":\"0\",\"left\":\"0\",\"isLinked\":false},\"flex_direction\":\"row\",\"flex_wrap_tablet\":\"wrap\",\"margin_tablet\":{\"unit\":\"px\",\"top\":\"0\",\"right\":\"0\",\"bottom\":\"70\",\"left\":\"0\",\"isLinked\":false}},\"elements\":[{\"id\":\"0840e01\",\"elType\":\"widget\",\"settings\":{\"image\":{\"url\":\"http://img.wpbrandy.com/uploads/wc-about-us-gallery-2.png\",\"id\":\"\",\"size\":\"\",\"source\":\"url\",\"alt\":\"\"}},\"elements\":[],\"widgetType\":\"image\"},{\"id\":\"12809cc\",\"elType\":\"widget\",\"settings\":{\"image\":{\"url\":\"http://img.wpbrandy.com/uploads/wc-about-us-gallery-1.png\",\"id\":\"\",\"size\":\"\",\"source\":\"url\",\"alt\":\"\"},\"image_custom_dimension\":{\"width\":\"1000\",\"height\":\"400\"}},\"elements\":[],\"widgetType\":\"image\"}],\"isInner\":false},{\"id\":\"fc388b8\",\"elType\":\"container\",\"settings\":{\"content_width\":\"full\",\"margin\":{\"unit\":\"px\",\"top\":\"0\",\"right\":\"0\",\"bottom\":\"150\",\"left\":\"0\",\"isLinked\":false},\"padding\":{\"unit\":\"px\",\"top\":\"0\",\"right\":\"0\",\"bottom\":\"0\",\"left\":\"0\",\"isLinked\":false},\"margin_tablet\":{\"unit\":\"px\",\"top\":\"0\",\"right\":\"0\",\"bottom\":\"70\",\"left\":\"0\",\"isLinked\":false}},\"elements\":[{\"id\":\"2879f12\",\"elType\":\"container\",\"settings\":{\"content_width\":\"full\",\"flex_direction\":\"row\",\"flex_gap\":{\"column\":\"3\",\"row\":\"3\",\"isLinked\":true,\"unit\":\"rem\",\"size\":3},\"grid_columns_grid\":{\"unit\":\"fr\",\"size\":9,\"sizes\":[]},\"padding\":{\"unit\":\"px\",\"top\":\"0\",\"right\":\"0\",\"bottom\":\"0\",\"left\":\"0\",\"isLinked\":false},\"css_classes\":\"builder-boxed\",\"presetTitle\":\"Container\",\"presetIcon\":\"eicon-container\",\"flex_gap_tablet\":{\"column\":\"\",\"row\":\"\",\"isLinked\":true,\"unit\":\"rem\",\"size\":null},\"flex_gap_mobile\":{\"column\":\"\",\"row\":\"\",\"isLinked\":true,\"unit\":\"rem\",\"size\":null}},\"elements\":[{\"id\":\"1cbc461\",\"elType\":\"container\",\"settings\":{\"content_width\":\"full\",\"padding\":{\"unit\":\"px\",\"top\":\"0\",\"right\":\"0\",\"bottom\":\"0\",\"left\":\"0\",\"isLinked\":false}},\"elements\":[{\"id\":\"83415cb\",\"elType\":\"widget\",\"settings\":{\"title\":\"Our Mission\",\"header_size\":\"h3\",\"typography_typography\":\"custom\",\"typography_font_size\":{\"unit\":\"px\",\"size\":24,\"sizes\":[]}},\"elements\":[],\"widgetType\":\"heading\"},{\"id\":\"cf716e6\",\"elType\":\"widget\",\"settings\":{\"editor\":\"<p>We help women change their appearance in a simple but elegant way, modern to improve life as well as meet friends.<\\/p>\",\"__globals__\":{\"text_color\":\"globals\\/colors?id=brandy_body_secondary\"}},\"elements\":[],\"widgetType\":\"text-editor\"}],\"isInner\":true},{\"id\":\"23eaee0\",\"elType\":\"container\",\"settings\":{\"content_width\":\"full\",\"padding\":{\"unit\":\"px\",\"top\":\"0\",\"right\":\"0\",\"bottom\":\"0\",\"left\":\"0\",\"isLinked\":false}},\"elements\":[{\"id\":\"c01f404\",\"elType\":\"widget\",\"settings\":{\"title\":\"Our Vision\",\"header_size\":\"h3\",\"typography_typography\":\"custom\",\"typography_font_size\":{\"unit\":\"px\",\"size\":24,\"sizes\":[]}},\"elements\":[],\"widgetType\":\"heading\"},{\"id\":\"dcabda7\",\"elType\":\"widget\",\"settings\":{\"editor\":\"<p>With the motto is simple. We exist to help clients accelerate their transformation with simple yet modern, luxurious designs.<\\/p>\",\"__globals__\":{\"text_color\":\"globals\\/colors?id=brandy_body_secondary\"}},\"elements\":[],\"widgetType\":\"text-editor\"}],\"isInner\":true},{\"id\":\"da8de69\",\"elType\":\"container\",\"settings\":{\"content_width\":\"full\",\"padding\":{\"unit\":\"px\",\"top\":\"0\",\"right\":\"0\",\"bottom\":\"0\",\"left\":\"0\",\"isLinked\":false}},\"elements\":[{\"id\":\"3e4d535\",\"elType\":\"widget\",\"settings\":{\"title\":\"Core Value\",\"header_size\":\"h3\",\"typography_typography\":\"custom\",\"typography_font_size\":{\"unit\":\"px\",\"size\":24,\"sizes\":[]}},\"elements\":[],\"widgetType\":\"heading\"},{\"id\":\"48bf0d5\",\"elType\":\"widget\",\"settings\":{\"editor\":\"<p>We help clients find products that are right for them to help them shine. And that\\u2019s why we\\u2019re a minimalism flagship store for women!<\\/p>\",\"__globals__\":{\"text_color\":\"globals\\/colors?id=brandy_body_secondary\"}},\"elements\":[],\"widgetType\":\"text-editor\"}],\"isInner\":true}],\"isInner\":true}],\"isInner\":false},{\"id\":\"e92fa19\",\"elType\":\"container\",\"settings\":{\"content_width\":\"full\",\"margin\":{\"unit\":\"px\",\"top\":\"0\",\"right\":\"0\",\"bottom\":\"150\",\"left\":\"0\",\"isLinked\":false},\"padding\":{\"unit\":\"px\",\"top\":\"0\",\"right\":\"0\",\"bottom\":\"0\",\"left\":\"0\",\"isLinked\":false},\"flex_gap\":{\"column\":\"0\",\"row\":\"0\",\"isLinked\":true,\"unit\":\"px\",\"size\":0},\"margin_tablet\":{\"unit\":\"px\",\"top\":\"0\",\"right\":\"0\",\"bottom\":\"70\",\"left\":\"0\",\"isLinked\":false}},\"elements\":[{\"id\":\"fda6065\",\"elType\":\"container\",\"settings\":{\"content_width\":\"full\",\"flex_direction\":\"column\",\"flex_gap\":{\"column\":\"2\",\"row\":\"2\",\"isLinked\":true,\"unit\":\"rem\",\"size\":2},\"grid_columns_grid\":{\"unit\":\"fr\",\"size\":9,\"sizes\":[]},\"padding\":{\"unit\":\"px\",\"top\":\"0\",\"right\":\"0\",\"bottom\":\"0\",\"left\":\"0\",\"isLinked\":false},\"css_classes\":\"builder-boxed\",\"presetTitle\":\"Container\",\"presetIcon\":\"eicon-container\",\"flex_gap_tablet\":{\"column\":\"\",\"row\":\"\",\"isLinked\":true,\"unit\":\"rem\",\"size\":null},\"flex_gap_mobile\":{\"column\":\"\",\"row\":\"\",\"isLinked\":true,\"unit\":\"rem\",\"size\":null}},\"elements\":[{\"id\":\"d000bd2\",\"elType\":\"widget\",\"settings\":{\"title\":\"We believe that people are essential.\",\"align\":\"center\",\"typography_typography\":\"custom\",\"typography_font_size\":{\"unit\":\"rem\",\"size\":2.25,\"sizes\":[]},\"typography_font_size_tablet\":{\"unit\":\"rem\",\"size\":2,\"sizes\":[]},\"typography_font_size_mobile\":{\"unit\":\"rem\",\"size\":\"\",\"sizes\":[]},\"typography_line_height\":{\"unit\":\"custom\",\"size\":\"1.33\",\"sizes\":[]},\"typography_line_height_tablet\":{\"unit\":\"custom\",\"size\":\"\",\"sizes\":[]},\"typography_line_height_mobile\":{\"unit\":\"custom\",\"size\":\"\",\"sizes\":[]}},\"elements\":[],\"widgetType\":\"heading\"},{\"id\":\"a540803\",\"elType\":\"container\",\"settings\":{\"content_width\":\"full\",\"flex_direction\":\"row\",\"flex_gap\":{\"column\":\"3\",\"row\":\"3\",\"isLinked\":true,\"unit\":\"rem\",\"size\":3},\"flex_gap_tablet\":{\"column\":\"\",\"row\":\"\",\"isLinked\":true,\"unit\":\"rem\",\"size\":null},\"flex_gap_mobile\":{\"column\":\"\",\"row\":\"\",\"isLinked\":true,\"unit\":\"rem\",\"size\":null},\"flex_wrap_tablet\":\"wrap\",\"padding\":{\"unit\":\"px\",\"top\":\"0\",\"right\":\"0\",\"bottom\":\"0\",\"left\":\"0\",\"isLinked\":false}},\"elements\":[{\"id\":\"608d916\",\"elType\":\"container\",\"settings\":{\"boxed_width_tablet\":{\"unit\":\"px\",\"size\":400,\"sizes\":[]},\"boxed_width_mobile\":{\"unit\":\"%\",\"size\":\"\",\"sizes\":[]},\"flex_direction\":\"column\",\"flex_gap\":{\"column\":\"0\",\"row\":\"0\",\"isLinked\":true,\"unit\":\"px\",\"size\":0},\"padding\":{\"unit\":\"px\",\"top\":\"0\",\"right\":\"0\",\"bottom\":\"0\",\"left\":\"0\",\"isLinked\":false}},\"elements\":[{\"id\":\"3ca0274\",\"elType\":\"widget\",\"settings\":{\"image\":{\"url\":\"http://img.wpbrandy.com/uploads/fashion-member-1.png\",\"id\":\"\",\"size\":\"\",\"source\":\"url\",\"alt\":\"\"},\"height\":{\"unit\":\"px\",\"size\":450,\"sizes\":[]},\"object-fit\":\"contain\",\"object-fit_tablet\":\"contain\",\"object-fit_mobile\":\"contain\",\"_margin\":{\"unit\":\"px\",\"top\":\"0\",\"right\":\"0\",\"bottom\":\"0\",\"left\":\"0\",\"isLinked\":false},\"_padding\":{\"unit\":\"px\",\"top\":\"0\",\"right\":\"0\",\"bottom\":\"0\",\"left\":\"0\",\"isLinked\":false},\"_background_background\":\"classic\",\"_background_color\":\"#EFF2F8\",\"_border_radius\":{\"unit\":\"rem\",\"top\":\"0.75\",\"right\":\"0.75\",\"bottom\":\"0.75\",\"left\":\"0.75\",\"isLinked\":false},\"_border_radius_tablet\":{\"unit\":\"rem\",\"top\":\"\",\"right\":\"\",\"bottom\":\"\",\"left\":\"\",\"isLinked\":true},\"_border_radius_mobile\":{\"unit\":\"rem\",\"top\":\"\",\"right\":\"\",\"bottom\":\"\",\"left\":\"\",\"isLinked\":true}},\"elements\":[],\"widgetType\":\"image\"},{\"id\":\"f24e4c7\",\"elType\":\"widget\",\"settings\":{\"title\":\"JENNY MATHEW\",\"header_size\":\"h4\",\"align\":\"center\",\"_margin\":{\"unit\":\"px\",\"top\":\"8\",\"right\":\"0\",\"bottom\":\"0\",\"left\":\"0\",\"isLinked\":false},\"_padding\":{\"unit\":\"px\",\"top\":\"0\",\"right\":\"0\",\"bottom\":\"0\",\"left\":\"0\",\"isLinked\":false}},\"elements\":[],\"widgetType\":\"heading\"},{\"id\":\"0501209\",\"elType\":\"widget\",\"settings\":{\"editor\":\"<p>Founder<\\/p>\",\"align\":\"center\",\"typography_typography\":\"custom\",\"typography_font_size\":{\"unit\":\"rem\",\"size\":0.875,\"sizes\":[]},\"typography_font_size_tablet\":{\"unit\":\"rem\",\"size\":\"\",\"sizes\":[]},\"typography_font_size_mobile\":{\"unit\":\"rem\",\"size\":\"\",\"sizes\":[]},\"__globals__\":{\"text_color\":\"globals\\/colors?id=brandy_body_secondary\"}},\"elements\":[],\"widgetType\":\"text-editor\"}],\"isInner\":true},{\"id\":\"8202d1b\",\"elType\":\"container\",\"settings\":{\"boxed_width_tablet\":{\"unit\":\"px\",\"size\":400,\"sizes\":[]},\"boxed_width_mobile\":{\"unit\":\"%\",\"size\":\"\",\"sizes\":[]},\"flex_direction\":\"column\",\"flex_gap\":{\"column\":\"0\",\"row\":\"0\",\"isLinked\":true,\"unit\":\"px\",\"size\":0},\"padding\":{\"unit\":\"px\",\"top\":\"0\",\"right\":\"0\",\"bottom\":\"0\",\"left\":\"0\",\"isLinked\":false}},\"elements\":[{\"id\":\"a769b2e\",\"elType\":\"widget\",\"settings\":{\"image\":{\"url\":\"http://img.wpbrandy.com/uploads/fashion-member-2.png\",\"id\":\"\",\"size\":\"\",\"source\":\"url\",\"alt\":\"\"},\"height\":{\"unit\":\"px\",\"size\":450,\"sizes\":[]},\"object-fit\":\"contain\",\"object-fit_tablet\":\"contain\",\"object-fit_mobile\":\"contain\",\"_margin\":{\"unit\":\"px\",\"top\":\"0\",\"right\":\"0\",\"bottom\":\"0\",\"left\":\"0\",\"isLinked\":false},\"_padding\":{\"unit\":\"px\",\"top\":\"0\",\"right\":\"0\",\"bottom\":\"0\",\"left\":\"0\",\"isLinked\":false},\"_background_background\":\"classic\",\"_background_color\":\"#EFF2F8\",\"_border_radius\":{\"unit\":\"rem\",\"top\":\"0.75\",\"right\":\"0.75\",\"bottom\":\"0.75\",\"left\":\"0.75\",\"isLinked\":false},\"_border_radius_tablet\":{\"unit\":\"rem\",\"top\":\"\",\"right\":\"\",\"bottom\":\"\",\"left\":\"\",\"isLinked\":true},\"_border_radius_mobile\":{\"unit\":\"rem\",\"top\":\"\",\"right\":\"\",\"bottom\":\"\",\"left\":\"\",\"isLinked\":true}},\"elements\":[],\"widgetType\":\"image\"},{\"id\":\"189b701\",\"elType\":\"widget\",\"settings\":{\"title\":\"AMANDA LOUISA\",\"header_size\":\"h4\",\"align\":\"center\",\"_margin\":{\"unit\":\"px\",\"top\":\"8\",\"right\":\"0\",\"bottom\":\"0\",\"left\":\"0\",\"isLinked\":false},\"_padding\":{\"unit\":\"px\",\"top\":\"0\",\"right\":\"0\",\"bottom\":\"0\",\"left\":\"0\",\"isLinked\":false}},\"elements\":[],\"widgetType\":\"heading\"},{\"id\":\"ef649b7\",\"elType\":\"widget\",\"settings\":{\"editor\":\"<div class=\\\"wp-block-column wc-about-us__members__item is-layout-flow wp-block-column-is-layout-flow\\\"><p class=\\\"has-text-align-center has-palette-4-color has-text-color has-link-color has-small-font-size wp-elements-7f06e953460cf62e1d2f29718fde89c5\\\">Managing Director<\\/p><\\/div>\",\"align\":\"center\",\"typography_typography\":\"custom\",\"typography_font_size\":{\"unit\":\"rem\",\"size\":0.875,\"sizes\":[]},\"typography_font_size_tablet\":{\"unit\":\"rem\",\"size\":\"\",\"sizes\":[]},\"typography_font_size_mobile\":{\"unit\":\"rem\",\"size\":\"\",\"sizes\":[]},\"__globals__\":{\"text_color\":\"globals\\/colors?id=brandy_body_secondary\"}},\"elements\":[],\"widgetType\":\"text-editor\"}],\"isInner\":true},{\"id\":\"9db69ff\",\"elType\":\"container\",\"settings\":{\"boxed_width_tablet\":{\"unit\":\"px\",\"size\":400,\"sizes\":[]},\"boxed_width_mobile\":{\"unit\":\"%\",\"size\":\"\",\"sizes\":[]},\"flex_direction\":\"column\",\"flex_gap\":{\"column\":\"0\",\"row\":\"0\",\"isLinked\":true,\"unit\":\"px\",\"size\":0},\"padding\":{\"unit\":\"px\",\"top\":\"0\",\"right\":\"0\",\"bottom\":\"0\",\"left\":\"0\",\"isLinked\":false}},\"elements\":[{\"id\":\"58b6768\",\"elType\":\"widget\",\"settings\":{\"image\":{\"url\":\"http://img.wpbrandy.com/uploads/fashion-member-3.png\",\"id\":\"\",\"size\":\"\",\"source\":\"url\",\"alt\":\"\"},\"height\":{\"unit\":\"px\",\"size\":450,\"sizes\":[]},\"object-fit\":\"contain\",\"object-fit_tablet\":\"contain\",\"object-fit_mobile\":\"contain\",\"_margin\":{\"unit\":\"px\",\"top\":\"0\",\"right\":\"0\",\"bottom\":\"0\",\"left\":\"0\",\"isLinked\":false},\"_padding\":{\"unit\":\"px\",\"top\":\"0\",\"right\":\"0\",\"bottom\":\"0\",\"left\":\"0\",\"isLinked\":false},\"_background_background\":\"classic\",\"_background_color\":\"#EFF2F8\",\"_border_radius\":{\"unit\":\"rem\",\"top\":\"0.75\",\"right\":\"0.75\",\"bottom\":\"0.75\",\"left\":\"0.75\",\"isLinked\":false},\"_border_radius_tablet\":{\"unit\":\"rem\",\"top\":\"\",\"right\":\"\",\"bottom\":\"\",\"left\":\"\",\"isLinked\":true},\"_border_radius_mobile\":{\"unit\":\"rem\",\"top\":\"\",\"right\":\"\",\"bottom\":\"\",\"left\":\"\",\"isLinked\":true}},\"elements\":[],\"widgetType\":\"image\"},{\"id\":\"b560fae\",\"elType\":\"widget\",\"settings\":{\"title\":\"JOHN EDWARD\",\"header_size\":\"h4\",\"align\":\"center\",\"_margin\":{\"unit\":\"px\",\"top\":\"8\",\"right\":\"0\",\"bottom\":\"0\",\"left\":\"0\",\"isLinked\":false},\"_padding\":{\"unit\":\"px\",\"top\":\"0\",\"right\":\"0\",\"bottom\":\"0\",\"left\":\"0\",\"isLinked\":false}},\"elements\":[],\"widgetType\":\"heading\"},{\"id\":\"0d3e1fc\",\"elType\":\"widget\",\"settings\":{\"editor\":\"<div class=\\\"wp-block-column wc-about-us__members__item is-layout-flow wp-block-column-is-layout-flow\\\"><p class=\\\"has-text-align-center has-palette-4-color has-text-color has-link-color has-small-font-size wp-elements-7457750d30bc7115817a0668657039c7\\\">UI\\/UX Designer<\\/p><\\/div>\",\"align\":\"center\",\"typography_typography\":\"custom\",\"typography_font_size\":{\"unit\":\"rem\",\"size\":0.875,\"sizes\":[]},\"typography_font_size_tablet\":{\"unit\":\"rem\",\"size\":\"\",\"sizes\":[]},\"typography_font_size_mobile\":{\"unit\":\"rem\",\"size\":\"\",\"sizes\":[]},\"__globals__\":{\"text_color\":\"globals\\/colors?id=brandy_body_secondary\"}},\"elements\":[],\"widgetType\":\"text-editor\"}],\"isInner\":true},{\"id\":\"f313b76\",\"elType\":\"container\",\"settings\":{\"boxed_width_tablet\":{\"unit\":\"px\",\"size\":400,\"sizes\":[]},\"boxed_width_mobile\":{\"unit\":\"%\",\"size\":\"\",\"sizes\":[]},\"flex_direction\":\"column\",\"flex_gap\":{\"column\":\"0\",\"row\":\"0\",\"isLinked\":true,\"unit\":\"px\",\"size\":0},\"padding\":{\"unit\":\"px\",\"top\":\"0\",\"right\":\"0\",\"bottom\":\"0\",\"left\":\"0\",\"isLinked\":false}},\"elements\":[{\"id\":\"67d9b10\",\"elType\":\"widget\",\"settings\":{\"image\":{\"url\":\"http://img.wpbrandy.com/uploads/fashion-member-4.png\",\"id\":\"\",\"size\":\"\",\"source\":\"url\",\"alt\":\"\"},\"height\":{\"unit\":\"px\",\"size\":450,\"sizes\":[]},\"object-fit\":\"contain\",\"object-fit_tablet\":\"contain\",\"object-fit_mobile\":\"contain\",\"_margin\":{\"unit\":\"px\",\"top\":\"0\",\"right\":\"0\",\"bottom\":\"0\",\"left\":\"0\",\"isLinked\":false},\"_padding\":{\"unit\":\"px\",\"top\":\"0\",\"right\":\"0\",\"bottom\":\"0\",\"left\":\"0\",\"isLinked\":false},\"_background_background\":\"classic\",\"_background_color\":\"#EFF2F8\",\"_border_radius\":{\"unit\":\"rem\",\"top\":\"0.75\",\"right\":\"0.75\",\"bottom\":\"0.75\",\"left\":\"0.75\",\"isLinked\":false},\"_border_radius_tablet\":{\"unit\":\"rem\",\"top\":\"\",\"right\":\"\",\"bottom\":\"\",\"left\":\"\",\"isLinked\":true},\"_border_radius_mobile\":{\"unit\":\"rem\",\"top\":\"\",\"right\":\"\",\"bottom\":\"\",\"left\":\"\",\"isLinked\":true}},\"elements\":[],\"widgetType\":\"image\"},{\"id\":\"a457f46\",\"elType\":\"widget\",\"settings\":{\"title\":\"MIRINDA ALEY\",\"header_size\":\"h4\",\"align\":\"center\",\"_margin\":{\"unit\":\"px\",\"top\":\"8\",\"right\":\"0\",\"bottom\":\"0\",\"left\":\"0\",\"isLinked\":false},\"_padding\":{\"unit\":\"px\",\"top\":\"0\",\"right\":\"0\",\"bottom\":\"0\",\"left\":\"0\",\"isLinked\":false}},\"elements\":[],\"widgetType\":\"heading\"},{\"id\":\"e50f0e4\",\"elType\":\"widget\",\"settings\":{\"editor\":\"<p>Chief Sale<\\/p>\",\"align\":\"center\",\"typography_typography\":\"custom\",\"typography_font_size\":{\"unit\":\"rem\",\"size\":0.875,\"sizes\":[]},\"typography_font_size_tablet\":{\"unit\":\"rem\",\"size\":\"\",\"sizes\":[]},\"typography_font_size_mobile\":{\"unit\":\"rem\",\"size\":\"\",\"sizes\":[]},\"__globals__\":{\"text_color\":\"globals\\/colors?id=brandy_body_secondary\"}},\"elements\":[],\"widgetType\":\"text-editor\"}],\"isInner\":true}],\"isInner\":true}],\"isInner\":true}],\"isInner\":false},{\"id\":\"5760d4f\",\"elType\":\"container\",\"settings\":{\"content_width\":\"full\",\"margin\":{\"unit\":\"px\",\"top\":\"0\",\"right\":\"0\",\"bottom\":\"150\",\"left\":\"0\",\"isLinked\":false},\"padding\":{\"unit\":\"px\",\"top\":\"0\",\"right\":\"0\",\"bottom\":\"0\",\"left\":\"0\",\"isLinked\":false},\"margin_tablet\":{\"unit\":\"px\",\"top\":\"0\",\"right\":\"0\",\"bottom\":\"70\",\"left\":\"0\",\"isLinked\":false}},\"elements\":[{\"id\":\"f191cdf\",\"elType\":\"container\",\"settings\":{\"content_width\":\"full\",\"flex_direction\":\"row\",\"flex_gap\":{\"column\":\"3\",\"row\":\"3\",\"isLinked\":true,\"unit\":\"rem\",\"size\":3},\"grid_columns_grid\":{\"unit\":\"fr\",\"size\":9,\"sizes\":[]},\"padding\":{\"unit\":\"px\",\"top\":\"0\",\"right\":\"0\",\"bottom\":\"0\",\"left\":\"0\",\"isLinked\":false},\"css_classes\":\"builder-boxed\",\"presetTitle\":\"Container\",\"presetIcon\":\"eicon-container\",\"flex_gap_tablet\":{\"column\":\"\",\"row\":\"\",\"isLinked\":true,\"unit\":\"rem\",\"size\":null},\"flex_gap_mobile\":{\"column\":\"\",\"row\":\"\",\"isLinked\":true,\"unit\":\"rem\",\"size\":null}},\"elements\":[{\"id\":\"02da9d7\",\"elType\":\"widget\",\"settings\":{\"image\":{\"url\":\"http://img.wpbrandy.com/uploads/wc-about-us-gallery-3.png\",\"id\":\"\",\"size\":\"\",\"source\":\"url\",\"alt\":\"\"}},\"elements\":[],\"widgetType\":\"image\"}],\"isInner\":true}],\"isInner\":false},{\"id\":\"5436b08\",\"elType\":\"container\",\"settings\":{\"content_width\":\"full\",\"margin\":{\"unit\":\"px\",\"top\":\"0\",\"right\":\"0\",\"bottom\":\"150\",\"left\":\"0\",\"isLinked\":false},\"padding\":{\"unit\":\"px\",\"top\":\"0\",\"right\":\"0\",\"bottom\":\"0\",\"left\":\"0\",\"isLinked\":false}},\"elements\":[{\"id\":\"3e555bc\",\"elType\":\"container\",\"settings\":{\"content_width\":\"full\",\"flex_direction\":\"row\",\"flex_gap\":{\"column\":\"4\",\"row\":\"4\",\"isLinked\":true,\"unit\":\"rem\",\"size\":4},\"grid_columns_grid\":{\"unit\":\"fr\",\"size\":9,\"sizes\":[]},\"padding\":{\"unit\":\"px\",\"top\":\"0\",\"right\":\"0\",\"bottom\":\"0\",\"left\":\"0\",\"isLinked\":false},\"css_classes\":\"builder-boxed\",\"presetTitle\":\"Container\",\"presetIcon\":\"eicon-container\",\"flex_gap_tablet\":{\"column\":\"\",\"row\":\"\",\"isLinked\":true,\"unit\":\"rem\",\"size\":null},\"flex_gap_mobile\":{\"column\":\"\",\"row\":\"\",\"isLinked\":true,\"unit\":\"rem\",\"size\":null}},\"elements\":[{\"id\":\"bd8564b\",\"elType\":\"container\",\"settings\":{\"content_width\":\"full\",\"width\":{\"unit\":\"%\",\"size\":39.275},\"padding\":{\"unit\":\"px\",\"top\":\"0\",\"right\":\"0\",\"bottom\":\"0\",\"left\":\"0\",\"isLinked\":false},\"_flex_size\":\"none\",\"_element_width\":\"initial\"},\"elements\":[{\"id\":\"08ac26d\",\"elType\":\"widget\",\"settings\":{\"title\":\"We believe that creating quality products is the key to our success.\\nWe\\u2019re Remit!\",\"align\":\"left\",\"typography_typography\":\"custom\",\"typography_font_size\":{\"unit\":\"rem\",\"size\":2.25,\"sizes\":[]},\"typography_font_size_tablet\":{\"unit\":\"rem\",\"size\":2,\"sizes\":[]},\"typography_font_size_mobile\":{\"unit\":\"rem\",\"size\":\"\",\"sizes\":[]},\"typography_line_height\":{\"unit\":\"custom\",\"size\":\"1.33\",\"sizes\":[]},\"typography_line_height_tablet\":{\"unit\":\"custom\",\"size\":\"\",\"sizes\":[]},\"typography_line_height_mobile\":{\"unit\":\"custom\",\"size\":\"\",\"sizes\":[]}},\"elements\":[],\"widgetType\":\"heading\"}],\"isInner\":true},{\"id\":\"709b648\",\"elType\":\"container\",\"settings\":{\"content_width\":\"full\",\"flex_gap\":{\"column\":\"1\",\"row\":\"1\",\"isLinked\":true,\"unit\":\"rem\",\"size\":1},\"flex_gap_tablet\":{\"column\":\"\",\"row\":\"\",\"isLinked\":true,\"unit\":\"rem\",\"size\":null},\"flex_gap_mobile\":{\"column\":\"\",\"row\":\"\",\"isLinked\":true,\"unit\":\"rem\",\"size\":null},\"padding\":{\"unit\":\"px\",\"top\":\"0\",\"right\":\"0\",\"bottom\":\"0\",\"left\":\"0\",\"isLinked\":false}},\"elements\":[{\"id\":\"9199823\",\"elType\":\"widget\",\"settings\":{\"title\":\"How will my parcel be delivered?\",\"header_size\":\"h4\",\"align\":\"left\",\"typography_typography\":\"custom\",\"typography_font_size\":{\"unit\":\"rem\",\"size\":\"\",\"sizes\":[]},\"typography_font_size_tablet\":{\"unit\":\"rem\",\"size\":\"\",\"sizes\":[]},\"typography_font_size_mobile\":{\"unit\":\"rem\",\"size\":\"\",\"sizes\":[]},\"typography_line_height\":{\"unit\":\"custom\",\"size\":\"1.33\",\"sizes\":[]},\"typography_line_height_tablet\":{\"unit\":\"custom\",\"size\":\"\",\"sizes\":[]},\"typography_line_height_mobile\":{\"unit\":\"custom\",\"size\":\"\",\"sizes\":[]}},\"elements\":[],\"widgetType\":\"heading\"},{\"id\":\"7f5b3b8\",\"elType\":\"widget\",\"settings\":{\"editor\":\"<p>We\\u2019ll cover duty costs on all orders. Additional taxes may apply according to local legislation. Please note the USA Express Free Shipping service cannot be used for International. If you have any further questions related to your delivery, please contact our Customer Care team.<\\/p>\",\"__globals__\":{\"text_color\":\"globals\\/colors?id=brandy_body_secondary\"}},\"elements\":[],\"widgetType\":\"text-editor\"}],\"isInner\":true}],\"isInner\":true}],\"isInner\":false}]"
  },
  {
    "ID": 4,
    "name": "brandy_wc_contact_us_elementor",
    "title": "[Elementor] WooCommerce Contact Us",
    "content": "",
    "elementor_data": "[{\"id\":\"114327c\",\"elType\":\"container\",\"settings\":{\"flex_gap\":{\"column\":\"0\",\"row\":\"0\",\"isLinked\":false,\"unit\":\"px\",\"size\":0},\"padding_mobile\":{\"unit\":\"px\",\"top\":\"0\",\"right\":\"0\",\"bottom\":\"0\",\"left\":\"0\",\"isLinked\":true},\"content_width\":\"full\",\"flex_direction\":\"row\",\"flex_justify_content\":\"center\",\"margin\":{\"unit\":\"px\",\"top\":\"100\",\"right\":\"0\",\"bottom\":\"0\",\"left\":\"0\",\"isLinked\":false},\"padding\":{\"unit\":\"px\",\"top\":\"0\",\"right\":\"0\",\"bottom\":\"0\",\"left\":\"0\",\"isLinked\":false}},\"elements\":[{\"id\":\"3e7fe57\",\"elType\":\"container\",\"settings\":{\"boxed_width\":{\"unit\":\"%\",\"size\":80,\"sizes\":[]},\"boxed_width_tablet\":{\"unit\":\"%\",\"size\":90,\"sizes\":[]},\"boxed_width_mobile\":{\"unit\":\"%\",\"size\":\"\",\"sizes\":[]},\"padding\":{\"unit\":\"px\",\"top\":\"0\",\"right\":\"0\",\"bottom\":\"0\",\"left\":\"0\",\"isLinked\":true},\"content_width\":\"full\",\"width\":{\"unit\":\"%\",\"size\":70,\"sizes\":[]},\"width_tablet\":{\"unit\":\"%\",\"size\":100,\"sizes\":[]},\"width_mobile\":{\"unit\":\"%\",\"size\":\"\",\"sizes\":[]},\"flex_gap\":{\"column\":\"0\",\"row\":\"0\",\"isLinked\":true,\"unit\":\"px\",\"size\":0}},\"elements\":[{\"id\":\"1371a46\",\"elType\":\"widget\",\"settings\":{\"title\":\"We're here to help you\",\"align\":\"center\",\"typography_typography\":\"custom\",\"typography_font_size\":{\"unit\":\"rem\",\"size\":2.25,\"sizes\":[]},\"typography_font_size_tablet\":{\"unit\":\"rem\",\"size\":2,\"sizes\":[]},\"typography_font_size_mobile\":{\"unit\":\"rem\",\"size\":\"\",\"sizes\":[]},\"_margin\":{\"unit\":\"px\",\"top\":\"0\",\"right\":\"0\",\"bottom\":\"10\",\"left\":\"0\",\"isLinked\":false},\"_padding\":{\"unit\":\"px\",\"top\":\"0\",\"right\":\"0\",\"bottom\":\"0\",\"left\":\"0\",\"isLinked\":false}},\"elements\":[],\"widgetType\":\"heading\"},{\"id\":\"ee6fcd9\",\"elType\":\"widget\",\"settings\":{\"editor\":\"<p>Have a question, comment, or brilliant idea you\\u2019d like to share? Please contact Remit using the most convenient way below:<\\/p><p><strong>Call us:<\\/strong> <a href=\\\"tel:6-146-389-574\\\">6-146-389-574<\\/a><\\/p><p><strong>Send us an email:<\\/strong>\\u00a0<a href=\\\"mailto:support@remit.com\\\">support@remit.com<\\/a><\\/p><p>Or fill out the form below and we\\u2019ll get back to you as soon as possible.<\\/p>\",\"align\":\"center\",\"_margin\":{\"unit\":\"px\",\"top\":\"0\",\"right\":\"0\",\"bottom\":\"30\",\"left\":\"0\",\"isLinked\":false},\"_padding\":{\"unit\":\"px\",\"top\":\"0\",\"right\":\"0\",\"bottom\":\"0\",\"left\":\"0\",\"isLinked\":false},\"__globals__\":{\"text_color\":\"globals\\/colors?id=brandy_body_secondary\"}},\"elements\":[],\"widgetType\":\"text-editor\"},{\"id\":\"bf1580a\",\"elType\":\"widget\",\"settings\":{\"form_name\":\"Contact form\",\"form_fields\":[{\"custom_id\":\"name\",\"field_label\":\"Full name\",\"placeholder\":\"Enter full name\",\"width\":\"50\",\"dynamic\":{\"active\":true},\"_id\":\"cc3f314\",\"required\":\"true\"},{\"custom_id\":\"email\",\"field_type\":\"tel\",\"required\":\"true\",\"field_label\":\"Phone number\",\"placeholder\":\"Enter phone number\",\"width\":\"50\",\"_id\":\"6bd7faf\"},{\"_id\":\"7dec074\",\"field_type\":\"email\",\"field_label\":\"Email address\",\"placeholder\":\"Enter email address\",\"required\":\"true\",\"width\":\"50\",\"custom_id\":\"field_7dec074\"},{\"_id\":\"e5e2905\",\"field_label\":\"Subject\",\"placeholder\":\"Enter your session\",\"required\":\"true\",\"width\":\"50\",\"custom_id\":\"field_e5e2905\"},{\"custom_id\":\"message\",\"field_type\":\"textarea\",\"field_label\":\"Message\",\"placeholder\":\"Message\",\"_id\":\"b4bd0c2\"}],\"mark_required\":\"yes\",\"button_align\":\"center\",\"step_next_label\":\"Next\",\"step_previous_label\":\"Previous\",\"button_text\":\"Submit\",\"email_to\":\"admin@brandy-dev.test\",\"email_subject\":\"New message from &quot;brandy-devs&quot;\",\"email_content\":\"[all-fields]\",\"email_from\":\"email@brandy-dev.test\",\"email_from_name\":\"brandy-devs\",\"email_to_2\":\"admin@brandy-dev.test\",\"email_subject_2\":\"New message from &quot;brandy-devs&quot;\",\"email_content_2\":\"[all-fields]\",\"email_from_2\":\"email@brandy-dev.test\",\"email_from_name_2\":\"brandy-devs\",\"email_reply_to_2\":\"admin@brandy-dev.test\",\"mailchimp_fields_map\":[],\"drip_fields_map\":[],\"activecampaign_fields_map\":[],\"getresponse_fields_map\":[],\"convertkit_fields_map\":[],\"mailerlite_fields_map\":[],\"success_message\":\"Your submission was successful.\",\"error_message\":\"Your submission failed because of an error.\",\"server_message\":\"Your submission failed because of a server error.\",\"invalid_message\":\"Your submission failed because the form is invalid.\",\"required_field_message\":\"This field is required.\",\"column_gap\":{\"unit\":\"px\",\"size\":15,\"sizes\":[]},\"row_gap\":{\"unit\":\"px\",\"size\":20,\"sizes\":[]},\"label_spacing\":{\"unit\":\"px\",\"size\":5,\"sizes\":[]},\"_margin\":{\"unit\":\"px\",\"top\":\"15\",\"right\":\"0\",\"bottom\":\"0\",\"left\":\"0\",\"isLinked\":false},\"field_border_width\":{\"unit\":\"px\",\"top\":\"1\",\"right\":\"1\",\"bottom\":\"1\",\"left\":\"1\",\"isLinked\":true},\"field_border_radius\":{\"unit\":\"px\",\"top\":\"10\",\"right\":\"10\",\"bottom\":\"10\",\"left\":\"10\",\"isLinked\":true},\"__globals__\":{\"field_border_color\":\"globals\\/colors?id=brandy_palette_6\"}},\"elements\":[],\"widgetType\":\"form\"}],\"isInner\":true}],\"isInner\":false}]"
  }
]
